[
  {
    "method": "BoTorch",
    "trial": 0,
    "status": "completed",
    "validation_loss": 0.5249409079551697,
    "num_layers": 3,
    "hidden_dim": 64,
    "layer_type": "GATED",
    "activation": "TANH",
    "pooling": "MEAN",
    "optimizer_type": "ADAM",
    "learning_rate": 0.0014066623362698203,
    "weight_decay": 1e-05,
    "batch_size": 16,
    "dropout": 0.041509146340181574,
    "elapsed_seconds": 23.970147004001774,
    "error": null,
    "x": [
      0.22895350709861106,
      0.09566431422085597,
      0.3670731417566211,
      0.8067948907310339,
      0.6414367243401504,
      0.21817354483959772,
      0.6710686045529061,
      0.6495888128554704,
      0.343501964976062,
      0.1660365853607263
    ]
  },
  {
    "method": "BoTorch",
    "trial": 1,
    "status": "completed",
    "validation_loss": 0.7222666144371033,
    "num_layers": 4,
    "hidden_dim": 64,
    "layer_type": "GATED",
    "activation": "TANH",
    "pooling": "ADD",
    "optimizer_type": "ADAM",
    "learning_rate": 0.0009883023990314643,
    "weight_decay": 1e-05,
    "batch_size": 16,
    "dropout": 0.2461257929159978,
    "elapsed_seconds": 35.027711055998225,
    "error": null,
    "x": [
      0.5623424482334707,
      0.24649214328559865,
      0.4584040025032281,
      0.9142324074644609,
      0.06583679466892545,
      0.583221009176559,
      0.5177685948644752,
      0.743749248627304,
      0.26649245047623993,
      0.9845031716639912
    ]
  },
  {
    "method": "BoTorch",
    "trial": 2,
    "status": "completed",
    "validation_loss": 1.4760105609893799,
    "num_layers": 5,
    "hidden_dim": 128,
    "layer_type": "GAT",
    "activation": "TANH",
    "pooling": "ADD",
    "optimizer_type": "ADAM",
    "learning_rate": 0.0026863250416328762,
    "weight_decay": 1e-05,
    "batch_size": 32,
    "dropout": 0.19876736754421626,
    "elapsed_seconds": 18.506359277002048,
    "error": null,
    "x": [
      0.9549241629984203,
      0.9392381912369776,
      0.7218067063902303,
      0.7256219689625525,
      0.22690663324956473,
      0.19386990381297287,
      0.9520373058270661,
      0.25666873803778845,
      0.6363869080103982,
      0.795069470176865
    ]
  },
  {
    "method": "BoTorch",
    "trial": 3,
    "status": "completed",
    "validation_loss": 0.920501708984375,
    "num_layers": 3,
    "hidden_dim": 128,
    "layer_type": "GAT",
    "activation": "RELU",
    "pooling": "ADD",
    "optimizer_type": "ADAM",
    "learning_rate": 0.0015505755911941828,
    "weight_decay": 1e-05,
    "batch_size": 16,
    "dropout": 0.018288690242811295,
    "elapsed_seconds": 15.95654410199495,
    "error": null,
    "x": [
      0.12551086709728987,
      0.9008668279919305,
      0.5236092886766213,
      0.40143349424272545,
      0.13654359689858442,
      0.48498707915192374,
      0.7133716884033708,
      0.9602667095115937,
      0.23316716131895399,
      0.07315476097124518
    ]
  },
  {
    "method": "BoTorch",
    "trial": 4,
    "status": "completed",
    "validation_loss": 1.0012470483779907,
    "num_layers": 5,
    "hidden_dim": 64,
    "layer_type": "GAT",
    "activation": "RELU",
    "pooling": "MEAN",
    "optimizer_type": "ADAM",
    "learning_rate": 0.0003105383507007304,
    "weight_decay": 1e-05,
    "batch_size": 32,
    "dropout": 0.0051486624473464915,
    "elapsed_seconds": 22.80491245497251,
    "error": null,
    "x": [
      0.7321412732596662,
      0.1514478514321107,
      0.5855822824638579,
      0.3807516740701189,
      0.747654255821885,
      0.23915206443721648,
      0.014993987374920636,
      0.7869224287325812,
      0.9363944644077339,
      0.020594649789385966
    ]
  },
  {
    "method": "BoTorch",
    "trial": 5,
    "status": "completed",
    "validation_loss": 0.6419958472251892,
    "num_layers": 3,
    "hidden_dim": 128,
    "layer_type": "GATED",
    "activation": "TANH",
    "pooling": "MEAN",
    "optimizer_type": "ADAM",
    "learning_rate": 0.0005137358030046816,
    "weight_decay": 1e-05,
    "batch_size": 16,
    "dropout": 0.008936500462751268,
    "elapsed_seconds": 18.643595520989038,
    "error": null,
    "x": [
      0.20505810188073137,
      0.9709643812395036,
      0.21882943318239023,
      0.7398458826338229,
      0.84363966925848,
      0.9714545448458801,
      0.23361857868140867,
      0.3781717641879978,
      0.01982344972784411,
      0.03574600185100507
    ]
  },
  {
    "method": "BoTorch",
    "trial": 6,
    "status": "completed",
    "validation_loss": 0.7947283387184143,
    "num_layers": 3,
    "hidden_dim": 64,
    "layer_type": "GATED",
    "activation": "RELU",
    "pooling": "MEAN",
    "optimizer_type": "ADAM",
    "learning_rate": 0.0006260469021714477,
    "weight_decay": 1e-05,
    "batch_size": 32,
    "dropout": 0.1152809766022761,
    "elapsed_seconds": 13.391166688001249,
    "error": null,
    "x": [
      0.07834054922624378,
      0.07890466480168112,
      0.2327079230231841,
      0.34283058830508617,
      0.6404641367005184,
      0.8344026362445967,
      0.31948561617641313,
      0.9087955151712707,
      0.5465895265401085,
      0.4611239064091044
    ]
  },
  {
    "method": "BoTorch",
    "trial": 7,
    "status": "completed",
    "validation_loss": 1.4218981266021729,
    "num_layers": 3,
    "hidden_dim": 128,
    "layer_type": "GAT",
    "activation": "TANH",
    "pooling": "MEAN",
    "optimizer_type": "ADAM",
    "learning_rate": 0.0014083298944452907,
    "weight_decay": 1e-05,
    "batch_size": 32,
    "dropout": 0.14368971051501264,
    "elapsed_seconds": 9.618468605040107,
    "error": null,
    "x": [
      0.31697963898008685,
      0.8809928502389176,
      0.5767603964876157,
      0.9728470570420368,
      0.6112327708373405,
      0.9508153006797765,
      0.6715831433787476,
      0.6270230359602764,
      0.7310019523069642,
      0.5747588420600506
    ]
  },
  {
    "method": "BoTorch",
    "trial": 8,
    "status": "completed",
    "validation_loss": 0.7210171818733215,
    "num_layers": 4,
    "hidden_dim": 64,
    "layer_type": "GAT",
    "activation": "RELU",
    "pooling": "ADD",
    "optimizer_type": "ADAM",
    "learning_rate": 0.0023382510020412183,
    "weight_decay": 1e-05,
    "batch_size": 16,
    "dropout": 0.1480913771486094,
    "elapsed_seconds": 36.725449779012706,
    "error": null,
    "x": [
      0.4257979641528039,
      0.49854271951068607,
      0.502221644047244,
      0.20400994582740217,
      0.28915168299698735,
      0.5743068550286677,
      0.8917698744117214,
      0.73394690525298,
      0.11857702415346794,
      0.5923655085944376
    ]
  },
  {
    "method": "BoTorch",
    "trial": 9,
    "status": "completed",
    "validation_loss": 2.5801146030426025,
    "num_layers": 4,
    "hidden_dim": 64,
    "layer_type": "GAT",
    "activation": "TANH",
    "pooling": "ADD",
    "optimizer_type": "ADAM",
    "learning_rate": 0.0003828641139679368,
    "weight_decay": 1e-05,
    "batch_size": 32,
    "dropout": 0.20986646895430278,
    "elapsed_seconds": 13.642855682992376,
    "error": null,
    "x": [
      0.6046198613481913,
      0.21859141029827844,
      0.7111155454884442,
      0.5050289267651028,
      0.1696676424440553,
      0.004291017185500623,
      0.10592340691118185,
      0.6610982645491772,
      0.5511251443325473,
      0.8394658758172111
    ]
  },
  {
    "method": "BoTorch",
    "trial": 10,
    "status": "completed",
    "validation_loss": 0.6549187898635864,
    "num_layers": 3,
    "hidden_dim": 64,
    "layer_type": "GATED",
    "activation": "RELU",
    "pooling": "MEAN",
    "optimizer_type": "ADAM",
    "learning_rate": 0.001628388347451349,
    "weight_decay": 1e-05,
    "batch_size": 16,
    "dropout": 0.1883121019514817,
    "elapsed_seconds": 17.26237311802106,
    "error": null,
    "x": [
      0.2662492782664301,
      0.21818378679757222,
      0.17159468153418866,
      0.40060210640036387,
      0.9118840964652495,
      0.6042824417888962,
      0.7346367312404101,
      0.021268978551058915,
      0.35046704129649153,
      0.7532484078059268
    ]
  },
  {
    "method": "BoTorch",
    "trial": 11,
    "status": "completed",
    "validation_loss": 0.5397298336029053,
    "num_layers": 4,
    "hidden_dim": 64,
    "layer_type": "GATED",
    "activation": "RELU",
    "pooling": "MEAN",
    "optimizer_type": "ADAM",
    "learning_rate": 0.00037592491168468513,
    "weight_decay": 1e-05,
    "batch_size": 16,
    "dropout": 0.07497923937775777,
    "elapsed_seconds": 41.8661843680311,
    "error": null,
    "x": [
      0.5287902358377834,
      0.4075510703494676,
      0.43228253482979984,
      0.10565379472895264,
      0.7597063629886803,
      0.4495900273206601,
      0.09797985165046863,
      0.6645112754916256,
      0.29367519616022386,
      0.2999169575110311
    ]
  },
  {
    "method": "BoTorch",
    "trial": 12,
    "status": "completed",
    "validation_loss": 0.5298323035240173,
    "num_layers": 5,
    "hidden_dim": 64,
    "layer_type": "GATED",
    "activation": "RELU",
    "pooling": "MEAN",
    "optimizer_type": "ADAM",
    "learning_rate": 0.00039510119758264715,
    "weight_decay": 1e-05,
    "batch_size": 16,
    "dropout": 0.06719906208747187,
    "elapsed_seconds": 44.38906667503761,
    "error": null,
    "x": [
      0.9066805453321412,
      0.13423343412140487,
      0.18500769915995774,
      0.14926769971366827,
      0.6439040723000565,
      0.7445735209863809,
      0.11958709134433732,
      0.1679442475062476,
      0.21978849371490106,
      0.26879624834988747
    ]
  },
  {
    "method": "BoTorch",
    "trial": 13,
    "status": "completed",
    "validation_loss": 1.916900396347046,
    "num_layers": 5,
    "hidden_dim": 64,
    "layer_type": "GAT",
    "activation": "TANH",
    "pooling": "ADD",
    "optimizer_type": "ADAM",
    "learning_rate": 0.0016867855611524551,
    "weight_decay": 1e-05,
    "batch_size": 16,
    "dropout": 0.23030500639184856,
    "elapsed_seconds": 28.301492400001734,
    "error": null,
    "x": [
      0.7272880445298088,
      0.3239773287262998,
      0.6569176685422717,
      0.6359845813651142,
      0.4306191853474358,
      0.89711517872504,
      0.7499386200877989,
      0.6100586192419336,
      0.13909137846226005,
      0.9212200255673942
    ]
  },
  {
    "method": "BoTorch",
    "trial": 14,
    "status": "completed",
    "validation_loss": 0.6782268285751343,
    "num_layers": 4,
    "hidden_dim": 64,
    "layer_type": "GATED",
    "activation": "TANH",
    "pooling": "ADD",
    "optimizer_type": "ADAM",
    "learning_rate": 0.0017087666602468995,
    "weight_decay": 1e-05,
    "batch_size": 32,
    "dropout": 0.04719329154911578,
    "elapsed_seconds": 11.144728377985302,
    "error": null,
    "x": [
      0.40065109584561376,
      0.17561655773304619,
      0.10324559470575356,
      0.9073131621429548,
      0.16982462788298913,
      0.6710015178113277,
      0.7555615071900995,
      0.6487276340612385,
      0.7839614988553194,
      0.18877316619646312
    ]
  },
  {
    "method": "BoTorch",
    "trial": 15,
    "status": "completed",
    "validation_loss": 0.7719525694847107,
    "num_layers": 3,
    "hidden_dim": 64,
    "layer_type": "GATED",
    "activation": "RELU",
    "pooling": "ADD",
    "optimizer_type": "ADAM",
    "learning_rate": 0.001865849849318392,
    "weight_decay": 1e-05,
    "batch_size": 16,
    "dropout": 0.01749090863913816,
    "elapsed_seconds": 12.24304663494695,
    "error": null,
    "x": [
      0.19494436456383224,
      0.3946788499671531,
      0.4587855520701971,
      0.23124579785600785,
      0.2427777096162943,
      0.27256352361543623,
      0.7937554370829861,
      0.6319343207559996,
      0.49403071168203083,
      0.06996363455655263
    ]
  },
  {
    "method": "BoTorch",
    "trial": 16,
    "status": "completed",
    "validation_loss": 0.646996796131134,
    "num_layers": 4,
    "hidden_dim": 64,
    "layer_type": "GAT",
    "activation": "RELU",
    "pooling": "MEAN",
    "optimizer_type": "ADAM",
    "learning_rate": 0.00035958547438300515,
    "weight_decay": 1e-05,
    "batch_size": 16,
    "dropout": 0.12036802233710381,
    "elapsed_seconds": 83.8292704320047,
    "error": null,
    "x": [
      0.5461271957393423,
      0.4032482186166997,
      0.8960308556933121,
      0.15315393079707118,
      0.5531929952120708,
      0.3606516665272387,
      0.07868088517489724,
      0.501227577529785,
      0.270750958658482,
      0.48147208934841523
    ]
  },
  {
    "method": "BoTorch",
    "trial": 17,
    "status": "completed",
    "validation_loss": 0.847969114780426,
    "num_layers": 5,
    "hidden_dim": 128,
    "layer_type": "GATED",
    "activation": "RELU",
    "pooling": "ADD",
    "optimizer_type": "ADAM",
    "learning_rate": 0.0025608953065168025,
    "weight_decay": 1e-05,
    "batch_size": 16,
    "dropout": 0.15437982872253111,
    "elapsed_seconds": 23.694158711994532,
    "error": null,
    "x": [
      0.7694610408898148,
      0.6416006602840669,
      0.3924494244400397,
      0.03463721555711308,
      0.4743528394674167,
      0.9161480764135054,
      0.9312705694608211,
      0.8343435068956319,
      0.03222344634380381,
      0.6175193148901245
    ]
  },
  {
    "method": "BoTorch",
    "trial": 18,
    "status": "completed",
    "validation_loss": 0.9800803065299988,
    "num_layers": 3,
    "hidden_dim": 64,
    "layer_type": "GAT",
    "activation": "TANH",
    "pooling": "ADD",
    "optimizer_type": "ADAM",
    "learning_rate": 0.0003454072844636268,
    "weight_decay": 1e-05,
    "batch_size": 32,
    "dropout": 0.0050092414041373046,
    "elapsed_seconds": 14.715561552962754,
    "error": null,
    "x": [
      0.0662339284222202,
      0.1757622007720513,
      0.6656051738852485,
      0.7621155705002205,
      0.060613382073311906,
      0.8116543177910776,
      0.06121023765768696,
      0.6926890009269331,
      0.8246311642268199,
      0.020036965616549218
    ]
  },
  {
    "method": "BoTorch",
    "trial": 19,
    "status": "completed",
    "validation_loss": 0.8725940585136414,
    "num_layers": 4,
    "hidden_dim": 128,
    "layer_type": "GATED",
    "activation": "TANH",
    "pooling": "ADD",
    "optimizer_type": "ADAM",
    "learning_rate": 0.0006847273733830467,
    "weight_decay": 1e-05,
    "batch_size": 32,
    "dropout": 0.24998799156626067,
    "elapsed_seconds": 13.106760146038141,
    "error": null,
    "x": [
      0.6378545971712937,
      0.6627158459958543,
      0.18191632609329011,
      0.8645421687291717,
      0.22927886685873045,
      0.05531700550722218,
      0.35839643530857224,
      0.015271558270300689,
      0.5786274433196582,
      0.9999519662650427
    ]
  },
  {
    "method": "BoTorch",
    "trial": 20,
    "status": "completed",
    "validation_loss": 0.5431720614433289,
    "num_layers": 3,
    "hidden_dim": 128,
    "layer_type": "GATED",
    "activation": "RELU",
    "pooling": "MEAN",
    "optimizer_type": "ADAM",
    "learning_rate": 0.001998921688182235,
    "weight_decay": 1e-05,
    "batch_size": 16,
    "dropout": 0.07223754061082624,
    "elapsed_seconds": 31.109223311999813,
    "error": null,
    "x": [
      0.28445930646901774,
      0.5047194026129326,
      0.0,
      0.2789320996129784,
      1.0,
      0.894961096731939,
      0.823674525363173,
      0.11367805863555644,
      0.12186586918502923,
      0.28895016244330496
    ]
  },
  {
    "method": "BoTorch",
    "trial": 21,
    "status": "completed",
    "validation_loss": 0.711749255657196,
    "num_layers": 3,
    "hidden_dim": 64,
    "layer_type": "GATED",
    "activation": "TANH",
    "pooling": "MEAN",
    "optimizer_type": "ADAM",
    "learning_rate": 0.00030000000000000014,
    "weight_decay": 1e-05,
    "batch_size": 16,
    "dropout": 0.0,
    "elapsed_seconds": 28.542341554013547,
    "error": null,
    "x": [
      0.0,
      0.22407556244640658,
      0.0,
      0.7906773064307864,
      1.0,
      0.8271084105357699,
      0.0,
      0.0,
      0.0,
      0.0
    ]
  },
  {
    "method": "BoTorch",
    "trial": 22,
    "status": "completed",
    "validation_loss": 1.0391603708267212,
    "num_layers": 3,
    "hidden_dim": 128,
    "layer_type": "GATED",
    "activation": "RELU",
    "pooling": "MEAN",
    "optimizer_type": "ADAM",
    "learning_rate": 0.003000000000000001,
    "weight_decay": 1e-05,
    "batch_size": 16,
    "dropout": 0.0,
    "elapsed_seconds": 14.930935989017598,
    "error": null,
    "x": [
      0.0,
      1.0,
      0.0,
      0.3436848005460885,
      0.6635343352562013,
      1.0,
      1.0,
      0.7558477397837859,
      0.0,
      0.0
    ]
  },
  {
    "method": "BoTorch",
    "trial": 23,
    "status": "completed",
    "validation_loss": 0.6863768100738525,
    "num_layers": 4,
    "hidden_dim": 64,
    "layer_type": "GATED",
    "activation": "RELU",
    "pooling": "MEAN",
    "optimizer_type": "ADAM",
    "learning_rate": 0.002739644635770468,
    "weight_decay": 1e-05,
    "batch_size": 16,
    "dropout": 0.1551814589750938,
    "elapsed_seconds": 30.329319690004922,
    "error": null,
    "x": [
      0.3524851361012577,
      0.13427855649493647,
      0.0,
      0.2524021709789637,
      1.0,
      0.712915635075172,
      0.960572978636161,
      0.0,
      0.2203239172852401,
      0.6207258359003752
    ]
  },
  {
    "method": "BoTorch",
    "trial": 24,
    "status": "completed",
    "validation_loss": 0.7044681310653687,
    "num_layers": 5,
    "hidden_dim": 64,
    "layer_type": "GATED",
    "activation": "TANH",
    "pooling": "MEAN",
    "optimizer_type": "ADAM",
    "learning_rate": 0.003000000000000001,
    "weight_decay": 1e-05,
    "batch_size": 16,
    "dropout": 0.0,
    "elapsed_seconds": 17.090773434960283,
    "error": null,
    "x": [
      0.9908627019173172,
      0.0,
      0.0,
      0.8334833292345531,
      0.5568690702989036,
      0.0,
      1.0,
      0.7027680948907373,
      0.0,
      0.0
    ]
  },
  {
    "method": "BoTorch",
    "trial": 25,
    "status": "completed",
    "validation_loss": 1.1892266273498535,
    "num_layers": 3,
    "hidden_dim": 128,
    "layer_type": "GATED",
    "activation": "RELU",
    "pooling": "MEAN",
    "optimizer_type": "ADAM",
    "learning_rate": 0.003000000000000001,
    "weight_decay": 1e-05,
    "batch_size": 16,
    "dropout": 0.12665105562505244,
    "elapsed_seconds": 10.954925749974791,
    "error": null,
    "x": [
      0.0,
      1.0,
      0.0,
      0.42413778116136724,
      1.0,
      1.0,
      1.0,
      0.0,
      0.0,
      0.5066042225002098
    ]
  },
  {
    "method": "BoTorch",
    "trial": 26,
    "status": "completed",
    "validation_loss": 0.594843327999115,
    "num_layers": 5,
    "hidden_dim": 64,
    "layer_type": "GATED",
    "activation": "RELU",
    "pooling": "MEAN",
    "optimizer_type": "ADAM",
    "learning_rate": 0.00030000000000000014,
    "weight_decay": 1e-05,
    "batch_size": 16,
    "dropout": 0.0,
    "elapsed_seconds": 46.54382761195302,
    "error": null,
    "x": [
      0.9343962965971474,
      0.4341266526248259,
      0.0,
      0.19715007805865783,
      0.7639478076940434,
      1.0,
      0.0,
      0.5993417916601568,
      0.17978939627130142,
      0.0
    ]
  },
  {
    "method": "BoTorch",
    "trial": 27,
    "status": "completed",
    "validation_loss": 3.236635208129883,
    "num_layers": 3,
    "hidden_dim": 64,
    "layer_type": "GAT",
    "activation": "TANH",
    "pooling": "MEAN",
    "optimizer_type": "ADAM",
    "learning_rate": 0.00030000000000000014,
    "weight_decay": 1e-05,
    "batch_size": 32,
    "dropout": 0.21819562771722506,
    "elapsed_seconds": 8.271592352015432,
    "error": null,
    "x": [
      0.0,
      0.0689458963871198,
      0.6335272766903409,
      0.8570977664214636,
      0.5079967649919225,
      0.0,
      0.0,
      0.2008441221621692,
      0.7407992339690705,
      0.8727825108689002
    ]
  },
  {
    "method": "BoTorch",
    "trial": 28,
    "status": "completed",
    "validation_loss": 0.6091570854187012,
    "num_layers": 4,
    "hidden_dim": 64,
    "layer_type": "GATED",
    "activation": "TANH",
    "pooling": "MEAN",
    "optimizer_type": "ADAM",
    "learning_rate": 0.002743110633931067,
    "weight_decay": 1e-05,
    "batch_size": 16,
    "dropout": 0.024989117142330406,
    "elapsed_seconds": 24.692434788972605,
    "error": null,
    "x": [
      0.4849372325254399,
      0.0,
      0.20847689070931008,
      0.859734999464804,
      0.760557045770745,
      0.26036344217676405,
      0.9611220690120418,
      0.6738149896977168,
      0.1680687216034311,
      0.09995646856932162
    ]
  },
  {
    "method": "BoTorch",
    "trial": 29,
    "status": "completed",
    "validation_loss": 0.9383783936500549,
    "num_layers": 5,
    "hidden_dim": 64,
    "layer_type": "GATED",
    "activation": "RELU",
    "pooling": "MEAN",
    "optimizer_type": "ADAM",
    "learning_rate": 0.003000000000000001,
    "weight_decay": 1e-05,
    "batch_size": 16,
    "dropout": 0.04969974035658744,
    "elapsed_seconds": 13.587714404973667,
    "error": null,
    "x": [
      1.0,
      0.40496994557941174,
      0.09027254615323296,
      0.0,
      1.0,
      0.3520723062074215,
      1.0,
      0.0,
      0.27434772235820326,
      0.19879896142634976
    ]
  },
  {
    "method": "BoTorch",
    "trial": 30,
    "status": "completed",
    "validation_loss": 1.5489155054092407,
    "num_layers": 5,
    "hidden_dim": 128,
    "layer_type": "GATED",
    "activation": "RELU",
    "pooling": "MEAN",
    "optimizer_type": "ADAM",
    "learning_rate": 0.003000000000000001,
    "weight_decay": 1e-05,
    "batch_size": 16,
    "dropout": 0.007209606529608857,
    "elapsed_seconds": 13.348902376019396,
    "error": null,
    "x": [
      0.7101496802265692,
      0.6643834091292367,
      0.11433346955466801,
      0.023778128418680176,
      1.0,
      0.8495184267350534,
      1.0,
      0.0,
      0.00987057715338424,
      0.02883842611843543
    ]
  },
  {
    "method": "BoTorch",
    "trial": 31,
    "status": "completed",
    "validation_loss": 0.5237964987754822,
    "num_layers": 5,
    "hidden_dim": 64,
    "layer_type": "GATED",
    "activation": "RELU",
    "pooling": "MEAN",
    "optimizer_type": "ADAM",
    "learning_rate": 0.0009289738654405433,
    "weight_decay": 1e-05,
    "batch_size": 32,
    "dropout": 0.07580730085184723,
    "elapsed_seconds": 17.84471879398916,
    "error": null,
    "x": [
      0.9132890416858526,
      0.0,
      0.0,
      0.0,
      1.0,
      0.5676670762492546,
      0.49088224156180266,
      0.4079963848368921,
      0.5487476684463288,
      0.3032292034073889
    ]
  },
  {
    "method": "BoTorch",
    "trial": 32,
    "status": "completed",
    "validation_loss": 0.5042538046836853,
    "num_layers": 4,
    "hidden_dim": 128,
    "layer_type": "GATED",
    "activation": "TANH",
    "pooling": "MEAN",
    "optimizer_type": "ADAM",
    "learning_rate": 0.00030000000000000014,
    "weight_decay": 1e-05,
    "batch_size": 16,
    "dropout": 0.01467218043153586,
    "elapsed_seconds": 42.956905088038184,
    "error": null,
    "x": [
      0.6520741576784419,
      0.5156563360928513,
      0.2897690656437303,
      1.0,
      0.7729586902023631,
      0.45890898673120273,
      0.0,
      0.0,
      0.08936620227397962,
      0.05868872172614344
    ]
  },
  {
    "method": "BoTorch",
    "trial": 33,
    "status": "completed",
    "validation_loss": 0.6710281372070312,
    "num_layers": 3,
    "hidden_dim": 64,
    "layer_type": "GATED",
    "activation": "TANH",
    "pooling": "ADD",
    "optimizer_type": "ADAM",
    "learning_rate": 0.0013420422507267253,
    "weight_decay": 1e-05,
    "batch_size": 16,
    "dropout": 0.062370218603921536,
    "elapsed_seconds": 21.30253988999175,
    "error": null,
    "x": [
      0.0,
      0.28524062369194525,
      0.0,
      0.5942816009035836,
      0.0,
      1.0,
      0.6506449339662398,
      1.0,
      0.40367054010549874,
      0.24948087441568614
    ]
  },
  {
    "method": "BoTorch",
    "trial": 34,
    "status": "completed",
    "validation_loss": 0.44704651832580566,
    "num_layers": 5,
    "hidden_dim": 64,
    "layer_type": "GATED",
    "activation": "TANH",
    "pooling": "MEAN",
    "optimizer_type": "ADAM",
    "learning_rate": 0.0007586013020106262,
    "weight_decay": 1e-05,
    "batch_size": 16,
    "dropout": 0.11007035568727919,
    "elapsed_seconds": 48.893173872027546,
    "error": null,
    "x": [
      1.0,
      0.0,
      0.12097514984348444,
      1.0,
      1.0,
      0.0,
      0.4028923290406566,
      0.0,
      0.16077924954176237,
      0.44028142274911675
    ]
  },
  {
    "method": "BoTorch",
    "trial": 35,
    "status": "completed",
    "validation_loss": 0.8901098370552063,
    "num_layers": 5,
    "hidden_dim": 64,
    "layer_type": "GATED",
    "activation": "TANH",
    "pooling": "ADD",
    "optimizer_type": "ADAM",
    "learning_rate": 0.0005643566407359498,
    "weight_decay": 1e-05,
    "batch_size": 16,
    "dropout": 0.0,
    "elapsed_seconds": 16.768684514972847,
    "error": null,
    "x": [
      1.0,
      0.10315193709867337,
      0.2568158006626343,
      1.0,
      0.0,
      0.0,
      0.27443238499681755,
      1.0,
      0.0,
      0.0
    ]
  },
  {
    "method": "BoTorch",
    "trial": 36,
    "status": "completed",
    "validation_loss": 0.6192739605903625,
    "num_layers": 3,
    "hidden_dim": 128,
    "layer_type": "GATED",
    "activation": "TANH",
    "pooling": "MEAN",
    "optimizer_type": "ADAM",
    "learning_rate": 0.00030000000000000014,
    "weight_decay": 1e-05,
    "batch_size": 16,
    "dropout": 0.0018719438928208414,
    "elapsed_seconds": 24.864408873021603,
    "error": null,
    "x": [
      0.0,
      1.0,
      0.28360133909640795,
      1.0,
      1.0,
      1.0,
      0.0,
      0.0,
      0.46009390544602746,
      0.0074877755712833656
    ]
  },
  {
    "method": "BoTorch",
    "trial": 37,
    "status": "completed",
    "validation_loss": 0.481050968170166,
    "num_layers": 4,
    "hidden_dim": 64,
    "layer_type": "GATED",
    "activation": "TANH",
    "pooling": "MEAN",
    "optimizer_type": "ADAM",
    "learning_rate": 0.0008499291606112807,
    "weight_decay": 1e-05,
    "batch_size": 16,
    "dropout": 0.11394993398470925,
    "elapsed_seconds": 32.41611343395198,
    "error": null,
    "x": [
      0.5055392535738871,
      0.055698475861324245,
      0.34811886106931905,
      1.0,
      1.0,
      0.0,
      0.45226147518558957,
      0.0,
      0.0,
      0.455799735938837
    ]
  },
  {
    "method": "BoTorch",
    "trial": 38,
    "status": "completed",
    "validation_loss": 1.089633822441101,
    "num_layers": 5,
    "hidden_dim": 128,
    "layer_type": "GATED",
    "activation": "TANH",
    "pooling": "MEAN",
    "optimizer_type": "ADAM",
    "learning_rate": 0.00030000000000000014,
    "weight_decay": 1e-05,
    "batch_size": 32,
    "dropout": 0.08030514130634586,
    "elapsed_seconds": 10.233521373011172,
    "error": null,
    "x": [
      1.0,
      0.6914193082204404,
      0.12331602251336267,
      1.0,
      1.0,
      0.19053806521095382,
      0.0,
      0.0,
      0.6142516846254314,
      0.32122056522538345
    ]
  },
  {
    "method": "BoTorch",
    "trial": 39,
    "status": "completed",
    "validation_loss": 0.575289249420166,
    "num_layers": 5,
    "hidden_dim": 64,
    "layer_type": "GATED",
    "activation": "TANH",
    "pooling": "MEAN",
    "optimizer_type": "ADAM",
    "learning_rate": 0.0005191682866754438,
    "weight_decay": 1e-05,
    "batch_size": 16,
    "dropout": 0.10680376043535145,
    "elapsed_seconds": 42.297695964050945,
    "error": null,
    "x": [
      0.9423639492816995,
      0.0,
      0.4222256393306087,
      1.0,
      1.0,
      0.40379036294265774,
      0.23818690106319823,
      0.0,
      0.0,
      0.4272150417414058
    ]
  },
  {
    "method": "BoTorch",
    "trial": 40,
    "status": "completed",
    "validation_loss": 1.0688531398773193,
    "num_layers": 5,
    "hidden_dim": 64,
    "layer_type": "GATED",
    "activation": "RELU",
    "pooling": "ADD",
    "optimizer_type": "ADAM",
    "learning_rate": 0.0005131771698371817,
    "weight_decay": 1e-05,
    "batch_size": 32,
    "dropout": 0.1090682060259954,
    "elapsed_seconds": 6.671948266972322,
    "error": null,
    "x": [
      1.0,
      0.0,
      0.14402355264966915,
      0.09172248681712784,
      0.0,
      0.10843488541248306,
      0.23314607257348816,
      0.0,
      1.0,
      0.4362728241039816
    ]
  },
  {
    "method": "BoTorch",
    "trial": 41,
    "status": "completed",
    "validation_loss": 0.6038191914558411,
    "num_layers": 3,
    "hidden_dim": 64,
    "layer_type": "GATED",
    "activation": "TANH",
    "pooling": "MEAN",
    "optimizer_type": "ADAM",
    "learning_rate": 0.0007469771704699296,
    "weight_decay": 1e-05,
    "batch_size": 16,
    "dropout": 0.0708463774517853,
    "elapsed_seconds": 25.104976437985897,
    "error": null,
    "x": [
      0.0,
      0.0,
      0.2360287205100633,
      1.0,
      1.0,
      1.0,
      0.39618607415003043,
      0.0,
      0.0,
      0.2833855098071412
    ]
  },
  {
    "method": "BoTorch",
    "trial": 42,
    "status": "completed",
    "validation_loss": 0.5400886535644531,
    "num_layers": 4,
    "hidden_dim": 64,
    "layer_type": "GATED",
    "activation": "RELU",
    "pooling": "MEAN",
    "optimizer_type": "ADAM",
    "learning_rate": 0.0009320709482406647,
    "weight_decay": 1e-05,
    "batch_size": 16,
    "dropout": 0.08778444634233605,
    "elapsed_seconds": 22.89795682299882,
    "error": null,
    "x": [
      0.6108270536161214,
      0.0,
      0.049567036950227884,
      0.269805457839986,
      1.0,
      0.6501552676322974,
      0.4923277169226098,
      0.4461732617936865,
      0.0,
      0.3511377853693442
    ]
  },
  {
    "method": "BoTorch",
    "trial": 43,
    "status": "completed",
    "validation_loss": 0.7780397534370422,
    "num_layers": 3,
    "hidden_dim": 128,
    "layer_type": "GATED",
    "activation": "TANH",
    "pooling": "MEAN",
    "optimizer_type": "ADAM",
    "learning_rate": 0.00030000000000000014,
    "weight_decay": 1e-05,
    "batch_size": 16,
    "dropout": 0.08988873076767771,
    "elapsed_seconds": 20.207359564956278,
    "error": null,
    "x": [
      0.0,
      0.7929560037009449,
      0.26858977388974886,
      1.0,
      1.0,
      0.0,
      0.0,
      0.0,
      0.03853813320178194,
      0.35955492307071085
    ]
  },
  {
    "method": "BoTorch",
    "trial": 44,
    "status": "completed",
    "validation_loss": 1.0800427198410034,
    "num_layers": 5,
    "hidden_dim": 64,
    "layer_type": "GATED",
    "activation": "TANH",
    "pooling": "MEAN",
    "optimizer_type": "ADAM",
    "learning_rate": 0.00030000000000000014,
    "weight_decay": 1e-05,
    "batch_size": 16,
    "dropout": 0.0948443257944155,
    "elapsed_seconds": 20.1690664239577,
    "error": null,
    "x": [
      1.0,
      0.0,
      0.1148808567893366,
      1.0,
      1.0,
      1.0,
      0.0,
      1.0,
      0.3405674399783503,
      0.379377303177662
    ]
  },
  {
    "method": "BoTorch",
    "trial": 45,
    "status": "completed",
    "validation_loss": 0.7346805334091187,
    "num_layers": 5,
    "hidden_dim": 64,
    "layer_type": "GATED",
    "activation": "TANH",
    "pooling": "ADD",
    "optimizer_type": "ADAM",
    "learning_rate": 0.001316779468815184,
    "weight_decay": 1e-05,
    "batch_size": 16,
    "dropout": 0.06350344831020079,
    "elapsed_seconds": 24.078940123028588,
    "error": null,
    "x": [
      1.0,
      0.12093822776820298,
      0.0,
      1.0,
      0.47448650065796244,
      0.09600866368822536,
      0.642391791695171,
      0.10291731443503065,
      0.26169863316860253,
      0.25401379324080314
    ]
  },
  {
    "method": "BoTorch",
    "trial": 46,
    "status": "completed",
    "validation_loss": 0.5460819602012634,
    "num_layers": 5,
    "hidden_dim": 64,
    "layer_type": "GATED",
    "activation": "TANH",
    "pooling": "MEAN",
    "optimizer_type": "ADAM",
    "learning_rate": 0.00147455695360767,
    "weight_decay": 1e-05,
    "batch_size": 16,
    "dropout": 0.11164010364284557,
    "elapsed_seconds": 22.360403486003634,
    "error": null,
    "x": [
      1.0,
      0.0,
      0.17681759902069316,
      1.0,
      1.0,
      0.0,
      0.6915402967763953,
      0.0,
      0.09756543056630898,
      0.4465604145713823
    ]
  },
  {
    "method": "BoTorch",
    "trial": 47,
    "status": "completed",
    "validation_loss": 0.6942918300628662,
    "num_layers": 3,
    "hidden_dim": 64,
    "layer_type": "GATED",
    "activation": "RELU",
    "pooling": "MEAN",
    "optimizer_type": "ADAM",
    "learning_rate": 0.0016510380363822692,
    "weight_decay": 1e-05,
    "batch_size": 16,
    "dropout": 0.04491761660166435,
    "elapsed_seconds": 14.158387147006579,
    "error": null,
    "x": [
      0.0,
      0.29689417967773246,
      0.0,
      0.0,
      1.0,
      1.0,
      0.7406358238736269,
      0.5549723469945245,
      0.4632211628290224,
      0.1796704664066574
    ]
  },
  {
    "method": "BoTorch",
    "trial": 48,
    "status": "completed",
    "validation_loss": 0.7078402042388916,
    "num_layers": 3,
    "hidden_dim": 64,
    "layer_type": "GATED",
    "activation": "RELU",
    "pooling": "MEAN",
    "optimizer_type": "ADAM",
    "learning_rate": 0.003000000000000001,
    "weight_decay": 1e-05,
    "batch_size": 16,
    "dropout": 0.17488333676280013,
    "elapsed_seconds": 14.21728078200249,
    "error": null,
    "x": [
      0.14319871845865864,
      0.0,
      0.0,
      0.0,
      1.0,
      0.14234954894653648,
      1.0,
      0.0,
      0.0,
      0.6995333470512005
    ]
  },
  {
    "method": "BoTorch",
    "trial": 49,
    "status": "completed",
    "validation_loss": 0.5050517916679382,
    "num_layers": 4,
    "hidden_dim": 64,
    "layer_type": "GATED",
    "activation": "RELU",
    "pooling": "MEAN",
    "optimizer_type": "ADAM",
    "learning_rate": 0.00033601412233533824,
    "weight_decay": 1e-05,
    "batch_size": 16,
    "dropout": 0.027629159227273783,
    "elapsed_seconds": 60.652523523021955,
    "error": null,
    "x": [
      0.6317649452172784,
      0.40702483881811385,
      0.33183781381269717,
      0.21680115258987906,
      0.8549911320617818,
      1.0,
      0.04923627601369332,
      0.40246267354865994,
      0.04828850507614248,
      0.11051663690909513
    ]
  },
  {
    "method": "BoTorch",
    "trial": 50,
    "status": "completed",
    "validation_loss": 0.7802271842956543,
    "num_layers": 4,
    "hidden_dim": 64,
    "layer_type": "GATED",
    "activation": "RELU",
    "pooling": "ADD",
    "optimizer_type": "ADAM",
    "learning_rate": 0.0006264151965263057,
    "weight_decay": 1e-05,
    "batch_size": 16,
    "dropout": 0.10130767748746047,
    "elapsed_seconds": 31.351881420996506,
    "error": null,
    "x": [
      0.6216050467501374,
      0.051250344150687265,
      0.3643320120840155,
      0.4594131145020163,
      0.4816025087024412,
      0.0,
      0.3197410302297525,
      0.14456089826010757,
      0.0,
      0.4052307099498419
    ]
  },
  {
    "method": "BoTorch",
    "trial": 51,
    "status": "completed",
    "validation_loss": 0.9853503704071045,
    "num_layers": 3,
    "hidden_dim": 64,
    "layer_type": "GATED",
    "activation": "TANH",
    "pooling": "MEAN",
    "optimizer_type": "ADAM",
    "learning_rate": 0.00034650467085954183,
    "weight_decay": 1e-05,
    "batch_size": 16,
    "dropout": 0.03167412273355475,
    "elapsed_seconds": 17.28456840896979,
    "error": null,
    "x": [
      0.0,
      0.0,
      0.0,
      1.0,
      0.7073016066224251,
      1.0,
      0.06258783852788163,
      0.5769600841889758,
      0.0,
      0.126696490934219
    ]
  },
  {
    "method": "BoTorch",
    "trial": 52,
    "status": "completed",
    "validation_loss": 0.49994146823883057,
    "num_layers": 4,
    "hidden_dim": 64,
    "layer_type": "GATED",
    "activation": "TANH",
    "pooling": "MEAN",
    "optimizer_type": "ADAM",
    "learning_rate": 0.0010124348205451813,
    "weight_decay": 1e-05,
    "batch_size": 16,
    "dropout": 0.10020771162660483,
    "elapsed_seconds": 26.573720255983062,
    "error": null,
    "x": [
      0.5070891476220329,
      0.43830328628884224,
      0.38719566702339614,
      1.0,
      1.0,
      0.9492887105524772,
      0.5282458186596548,
      0.40273294018164774,
      0.26787066870120824,
      0.4008308465064193
    ]
  },
  {
    "method": "BoTorch",
    "trial": 53,
    "status": "completed",
    "validation_loss": 0.47563567757606506,
    "num_layers": 5,
    "hidden_dim": 64,
    "layer_type": "GATED",
    "activation": "RELU",
    "pooling": "MEAN",
    "optimizer_type": "ADAM",
    "learning_rate": 0.0011201825200095185,
    "weight_decay": 1e-05,
    "batch_size": 16,
    "dropout": 0.07186379191342088,
    "elapsed_seconds": 49.055775041983,
    "error": null,
    "x": [
      1.0,
      0.21777755716068445,
      0.0,
      0.0,
      1.0,
      0.0,
      0.5721675366780116,
      0.0,
      0.0,
      0.2874551676536835
    ]
  },
  {
    "method": "BoTorch",
    "trial": 54,
    "status": "completed",
    "validation_loss": 0.45983195304870605,
    "num_layers": 5,
    "hidden_dim": 64,
    "layer_type": "GATED",
    "activation": "RELU",
    "pooling": "MEAN",
    "optimizer_type": "ADAM",
    "learning_rate": 0.0013317426634159677,
    "weight_decay": 1e-05,
    "batch_size": 16,
    "dropout": 0.1239287160554758,
    "elapsed_seconds": 37.557992966030724,
    "error": null,
    "x": [
      1.0,
      0.0,
      0.08270282684806683,
      0.0,
      1.0,
      0.0,
      0.6472990582110264,
      0.0,
      0.20266182842853847,
      0.4957148642219032
    ]
  },
  {
    "method": "BoTorch",
    "trial": 55,
    "status": "completed",
    "validation_loss": 0.5693529844284058,
    "num_layers": 4,
    "hidden_dim": 64,
    "layer_type": "GATED",
    "activation": "TANH",
    "pooling": "MEAN",
    "optimizer_type": "ADAM",
    "learning_rate": 0.0007546689150317369,
    "weight_decay": 1e-05,
    "batch_size": 16,
    "dropout": 0.02916796885867364,
    "elapsed_seconds": 26.710768892022315,
    "error": null,
    "x": [
      0.53563045453698,
      0.30628491418091486,
      0.39002445217353376,
      1.0,
      1.0,
      0.0,
      0.40063520696086047,
      0.6861578857131972,
      0.06733543292245449,
      0.11667187543469457
    ]
  },
  {
    "method": "BoTorch",
    "trial": 56,
    "status": "completed",
    "validation_loss": 0.5327686071395874,
    "num_layers": 5,
    "hidden_dim": 64,
    "layer_type": "GATED",
    "activation": "RELU",
    "pooling": "MEAN",
    "optimizer_type": "ADAM",
    "learning_rate": 0.0009685672563193717,
    "weight_decay": 1e-05,
    "batch_size": 16,
    "dropout": 0.08409128903294379,
    "elapsed_seconds": 24.68402879900532,
    "error": null,
    "x": [
      1.0,
      0.0,
      0.0763716458088299,
      0.4161586290323951,
      1.0,
      0.0,
      0.5090085283470616,
      0.0,
      0.2874783736491236,
      0.33636515613177514
    ]
  },
  {
    "method": "BoTorch",
    "trial": 57,
    "status": "completed",
    "validation_loss": 0.5553109645843506,
    "num_layers": 5,
    "hidden_dim": 64,
    "layer_type": "GATED",
    "activation": "TANH",
    "pooling": "MEAN",
    "optimizer_type": "ADAM",
    "learning_rate": 0.0008197190176783749,
    "weight_decay": 1e-05,
    "batch_size": 16,
    "dropout": 0.15551668493721402,
    "elapsed_seconds": 33.52761466399534,
    "error": null,
    "x": [
      1.0,
      0.0,
      0.0,
      0.7473900519276775,
      1.0,
      0.0,
      0.43654375622027886,
      0.0,
      0.392187882427304,
      0.6220667397488561
    ]
  },
  {
    "method": "BoTorch",
    "trial": 58,
    "status": "completed",
    "validation_loss": 0.685085117816925,
    "num_layers": 5,
    "hidden_dim": 64,
    "layer_type": "GATED",
    "activation": "RELU",
    "pooling": "MEAN",
    "optimizer_type": "ADAM",
    "learning_rate": 0.00030000000000000014,
    "weight_decay": 1e-05,
    "batch_size": 16,
    "dropout": 0.11976384183001078,
    "elapsed_seconds": 35.65964215202257,
    "error": null,
    "x": [
      1.0,
      0.32044602797947114,
      0.00808782805759784,
      0.0,
      1.0,
      0.21940035568245694,
      0.0,
      0.42762239270775804,
      0.0,
      0.4790553673200431
    ]
  },
  {
    "method": "BoTorch",
    "trial": 59,
    "status": "completed",
    "validation_loss": 0.7769143581390381,
    "num_layers": 3,
    "hidden_dim": 128,
    "layer_type": "GATED",
    "activation": "TANH",
    "pooling": "ADD",
    "optimizer_type": "ADAM",
    "learning_rate": 0.00030000000000000014,
    "weight_decay": 1e-05,
    "batch_size": 16,
    "dropout": 0.0,
    "elapsed_seconds": 23.085515015991405,
    "error": null,
    "x": [
      0.0,
      0.8572290283960435,
      0.267952094401266,
      1.0,
      0.463077709624174,
      1.0,
      0.0,
      0.5587718428856776,
      0.47636690694472217,
      0.0
    ]
  },
  {
    "method": "BoTorch",
    "trial": 60,
    "status": "completed",
    "validation_loss": 0.5720360279083252,
    "num_layers": 3,
    "hidden_dim": 64,
    "layer_type": "GATED",
    "activation": "TANH",
    "pooling": "MEAN",
    "optimizer_type": "ADAM",
    "learning_rate": 0.0022637692603234214,
    "weight_decay": 1e-05,
    "batch_size": 16,
    "dropout": 0.1597911231815707,
    "elapsed_seconds": 23.44086320704082,
    "error": null,
    "x": [
      0.15472565063102894,
      0.0,
      0.40014328107162606,
      1.0,
      1.0,
      0.0,
      0.8777109036291106,
      0.4357597293566497,
      0.4955963850650957,
      0.6391644927262828
    ]
  },
  {
    "method": "BoTorch",
    "trial": 61,
    "status": "completed",
    "validation_loss": 0.6900980472564697,
    "num_layers": 5,
    "hidden_dim": 64,
    "layer_type": "GATED",
    "activation": "RELU",
    "pooling": "MEAN",
    "optimizer_type": "ADAM",
    "learning_rate": 0.0005905415357587403,
    "weight_decay": 1e-05,
    "batch_size": 32,
    "dropout": 0.0,
    "elapsed_seconds": 14.927242817997467,
    "error": null,
    "x": [
      1.0,
      0.22291783666015322,
      0.3221203735263039,
      0.2958708338555015,
      1.0,
      0.8266139693788025,
      0.29412919442111524,
      0.0,
      0.5628380009961748,
      0.0
    ]
  },
  {
    "method": "BoTorch",
    "trial": 62,
    "status": "completed",
    "validation_loss": 0.6536226272583008,
    "num_layers": 3,
    "hidden_dim": 64,
    "layer_type": "GATED",
    "activation": "TANH",
    "pooling": "MEAN",
    "optimizer_type": "ADAM",
    "learning_rate": 0.0006516324967123781,
    "weight_decay": 1e-05,
    "batch_size": 16,
    "dropout": 0.11297926977289112,
    "elapsed_seconds": 21.923636754974723,
    "error": null,
    "x": [
      0.26085506301240297,
      0.27957750704631856,
      0.3470436006672769,
      1.0,
      1.0,
      0.5396724839164918,
      0.3368814795892324,
      0.28690108368477685,
      0.0,
      0.4519170790915645
    ]
  },
  {
    "method": "BoTorch",
    "trial": 63,
    "status": "completed",
    "validation_loss": 0.7894800901412964,
    "num_layers": 3,
    "hidden_dim": 64,
    "layer_type": "GATED",
    "activation": "TANH",
    "pooling": "MEAN",
    "optimizer_type": "ADAM",
    "learning_rate": 0.003000000000000001,
    "weight_decay": 1e-05,
    "batch_size": 32,
    "dropout": 0.0622766507946036,
    "elapsed_seconds": 5.73807494196808,
    "error": null,
    "x": [
      0.0,
      0.0,
      0.24550618913196118,
      1.0,
      1.0,
      0.0,
      1.0,
      1.0,
      0.79336410254977,
      0.2491066031784144
    ]
  },
  {
    "method": "BoTorch",
    "trial": 64,
    "status": "completed",
    "validation_loss": 0.646599531173706,
    "num_layers": 5,
    "hidden_dim": 64,
    "layer_type": "GATED",
    "activation": "TANH",
    "pooling": "MEAN",
    "optimizer_type": "ADAM",
    "learning_rate": 0.00235205204128259,
    "weight_decay": 1e-05,
    "batch_size": 16,
    "dropout": 0.09624225351128582,
    "elapsed_seconds": 22.35268965299474,
    "error": null,
    "x": [
      1.0,
      0.0,
      0.4210651583048691,
      1.0,
      1.0,
      1.0,
      0.8943256719496684,
      0.0,
      0.007849060851451933,
      0.3849690140451433
    ]
  },
  {
    "method": "BoTorch",
    "trial": 65,
    "status": "completed",
    "validation_loss": 0.5520185828208923,
    "num_layers": 5,
    "hidden_dim": 64,
    "layer_type": "GATED",
    "activation": "TANH",
    "pooling": "MEAN",
    "optimizer_type": "ADAM",
    "learning_rate": 0.0009341528499073397,
    "weight_decay": 1e-05,
    "batch_size": 16,
    "dropout": 0.05092498870223842,
    "elapsed_seconds": 35.52422244398622,
    "error": null,
    "x": [
      1.0,
      0.0,
      0.20348029529524728,
      0.5422737253438538,
      0.5997952271412454,
      0.0,
      0.49329668836287643,
      0.0,
      0.0,
      0.20369995480895367
    ]
  },
  {
    "method": "BoTorch",
    "trial": 66,
    "status": "completed",
    "validation_loss": 0.6645222902297974,
    "num_layers": 5,
    "hidden_dim": 64,
    "layer_type": "GATED",
    "activation": "RELU",
    "pooling": "ADD",
    "optimizer_type": "ADAM",
    "learning_rate": 0.0009266090743401302,
    "weight_decay": 1e-05,
    "batch_size": 16,
    "dropout": 0.1629387295357392,
    "elapsed_seconds": 28.386909610999282,
    "error": null,
    "x": [
      1.0,
      0.0,
      0.11088348332120276,
      0.2364707237942666,
      0.15431479974834147,
      0.0,
      0.48977529424109384,
      0.0,
      0.0065780521653413275,
      0.6517549181429568
    ]
  },
  {
    "method": "BoTorch",
    "trial": 67,
    "status": "completed",
    "validation_loss": 0.5650491118431091,
    "num_layers": 5,
    "hidden_dim": 128,
    "layer_type": "GATED",
    "activation": "RELU",
    "pooling": "MEAN",
    "optimizer_type": "ADAM",
    "learning_rate": 0.00030000000000000014,
    "weight_decay": 1e-05,
    "batch_size": 16,
    "dropout": 0.0,
    "elapsed_seconds": 47.68524045497179,
    "error": null,
    "x": [
      1.0,
      0.6035025331709062,
      0.24817175148844742,
      0.0,
      1.0,
      1.0,
      0.0,
      0.0,
      0.0,
      0.0
    ]
  },
  {
    "method": "BoTorch",
    "trial": 68,
    "status": "completed",
    "validation_loss": 0.6212721467018127,
    "num_layers": 3,
    "hidden_dim": 64,
    "layer_type": "GATED",
    "activation": "RELU",
    "pooling": "MEAN",
    "optimizer_type": "ADAM",
    "learning_rate": 0.002116367484362387,
    "weight_decay": 1e-05,
    "batch_size": 16,
    "dropout": 0.10853005434238783,
    "elapsed_seconds": 21.902200303971767,
    "error": null,
    "x": [
      0.18920007670207287,
      0.0,
      0.18805635896035552,
      0.15781017946424145,
      0.6871726783970226,
      0.0,
      0.8484698257388873,
      0.5894429741933904,
      0.14635675518692887,
      0.4341202173695513
    ]
  },
  {
    "method": "BoTorch",
    "trial": 69,
    "status": "completed",
    "validation_loss": 0.6585078835487366,
    "num_layers": 3,
    "hidden_dim": 64,
    "layer_type": "GATED",
    "activation": "RELU",
    "pooling": "MEAN",
    "optimizer_type": "ADAM",
    "learning_rate": 0.0013428284733016645,
    "weight_decay": 1e-05,
    "batch_size": 16,
    "dropout": 0.1486131223763641,
    "elapsed_seconds": 18.77936907100957,
    "error": null,
    "x": [
      0.0853740027405568,
      0.19713100695572514,
      0.02785201664137286,
      0.0,
      1.0,
      0.2073430500193205,
      0.6508992867233749,
      0.07444534806860627,
      0.1754197102677142,
      0.5944524895054564
    ]
  },
  {
    "method": "BoTorch",
    "trial": 70,
    "status": "completed",
    "validation_loss": 0.9629449248313904,
    "num_layers": 5,
    "hidden_dim": 64,
    "layer_type": "GAT",
    "activation": "RELU",
    "pooling": "MEAN",
    "optimizer_type": "ADAM",
    "learning_rate": 0.0005833176333308438,
    "weight_decay": 1e-05,
    "batch_size": 16,
    "dropout": 0.06082562936037535,
    "elapsed_seconds": 45.03570040402701,
    "error": null,
    "x": [
      0.9858774166853211,
      0.3419769833647535,
      0.9120553189390471,
      0.0,
      0.7769337932407749,
      1.0,
      0.28878385036204635,
      0.03561072159716576,
      0.0,
      0.2433025174415014
    ]
  },
  {
    "method": "BoTorch",
    "trial": 71,
    "status": "completed",
    "validation_loss": 0.5454858541488647,
    "num_layers": 5,
    "hidden_dim": 64,
    "layer_type": "GATED",
    "activation": "RELU",
    "pooling": "MEAN",
    "optimizer_type": "ADAM",
    "learning_rate": 0.001633140160015142,
    "weight_decay": 1e-05,
    "batch_size": 16,
    "dropout": 0.09026710559104056,
    "elapsed_seconds": 33.41050016699592,
    "error": null,
    "x": [
      1.0,
      0.4065788142062441,
      0.3490086945735627,
      0.0,
      0.8936025421150255,
      0.9100155564707761,
      0.7359022038131166,
      0.9547672022992807,
      0.0,
      0.36106842236416226
    ]
  },
  {
    "method": "BoTorch",
    "trial": 72,
    "status": "completed",
    "validation_loss": 0.5630362033843994,
    "num_layers": 5,
    "hidden_dim": 64,
    "layer_type": "GAT",
    "activation": "RELU",
    "pooling": "MEAN",
    "optimizer_type": "ADAM",
    "learning_rate": 0.00030000000000000014,
    "weight_decay": 1e-05,
    "batch_size": 16,
    "dropout": 0.08655691174616963,
    "elapsed_seconds": 135.5784371960326,
    "error": null,
    "x": [
      0.7667996975191751,
      0.27637144296816446,
      0.5653627286211025,
      0.0,
      1.0,
      0.9490026772822225,
      0.0,
      0.0,
      0.0,
      0.3462276469846785
    ]
  },
  {
    "method": "BoTorch",
    "trial": 73,
    "status": "completed",
    "validation_loss": 0.6008597016334534,
    "num_layers": 5,
    "hidden_dim": 128,
    "layer_type": "GATED",
    "activation": "RELU",
    "pooling": "MEAN",
    "optimizer_type": "ADAM",
    "learning_rate": 0.0004129984871791985,
    "weight_decay": 1e-05,
    "batch_size": 16,
    "dropout": 0.03474684800922865,
    "elapsed_seconds": 33.011901388992555,
    "error": null,
    "x": [
      1.0,
      0.5948922905890487,
      0.09571931362361841,
      0.0,
      1.0,
      0.0,
      0.1388272061112434,
      0.0,
      0.0,
      0.1389873920369146
    ]
  },
  {
    "method": "BoTorch",
    "trial": 74,
    "status": "completed",
    "validation_loss": 0.5915566086769104,
    "num_layers": 5,
    "hidden_dim": 64,
    "layer_type": "GATED",
    "activation": "RELU",
    "pooling": "MEAN",
    "optimizer_type": "ADAM",
    "learning_rate": 0.0014136778818852808,
    "weight_decay": 1e-05,
    "batch_size": 16,
    "dropout": 0.08163370349265714,
    "elapsed_seconds": 31.23644544999115,
    "error": null,
    "x": [
      1.0,
      0.25117310819100447,
      0.28871828986275544,
      0.132765723190528,
      1.0,
      1.0,
      0.6732292084494605,
      0.0,
      0.13952430825081313,
      0.32653481397062856
    ]
  },
  {
    "method": "BoTorch",
    "trial": 75,
    "status": "completed",
    "validation_loss": 0.8781306147575378,
    "num_layers": 5,
    "hidden_dim": 64,
    "layer_type": "GATED",
    "activation": "TANH",
    "pooling": "ADD",
    "optimizer_type": "ADAM",
    "learning_rate": 0.0021986035322376514,
    "weight_decay": 1e-05,
    "batch_size": 16,
    "dropout": 0.24174335794681548,
    "elapsed_seconds": 15.396563356043771,
    "error": null,
    "x": [
      0.6969757362668555,
      0.07554648715417678,
      0.27621417155756683,
      0.8835512271398432,
      0.0,
      0.8549467947673673,
      0.8650256666442179,
      1.0,
      0.0,
      0.9669734317872619
    ]
  },
  {
    "method": "BoTorch",
    "trial": 76,
    "status": "completed",
    "validation_loss": 1.0055099725723267,
    "num_layers": 3,
    "hidden_dim": 128,
    "layer_type": "GAT",
    "activation": "TANH",
    "pooling": "MEAN",
    "optimizer_type": "ADAM",
    "learning_rate": 0.0007377568220719317,
    "weight_decay": 1e-05,
    "batch_size": 16,
    "dropout": 0.07301998677680364,
    "elapsed_seconds": 29.28399411099963,
    "error": null,
    "x": [
      0.0,
      0.801203353333511,
      0.5096423818493592,
      1.0,
      1.0,
      0.0,
      0.3907919794123431,
      0.0,
      0.0,
      0.2920799471072146
    ]
  },
  {
    "method": "BoTorch",
    "trial": 77,
    "status": "completed",
    "validation_loss": 0.532814085483551,
    "num_layers": 5,
    "hidden_dim": 64,
    "layer_type": "GATED",
    "activation": "TANH",
    "pooling": "MEAN",
    "optimizer_type": "ADAM",
    "learning_rate": 0.000854411965949817,
    "weight_decay": 1e-05,
    "batch_size": 16,
    "dropout": 0.1660373702691258,
    "elapsed_seconds": 31.17505312297726,
    "error": null,
    "x": [
      1.0,
      0.0,
      0.11563424524202894,
      0.9853137601140138,
      1.0,
      0.0,
      0.4545460672560009,
      0.0,
      0.0,
      0.6641494810765032
    ]
  },
  {
    "method": "BoTorch",
    "trial": 78,
    "status": "completed",
    "validation_loss": 0.7390138506889343,
    "num_layers": 5,
    "hidden_dim": 64,
    "layer_type": "GATED",
    "activation": "RELU",
    "pooling": "MEAN",
    "optimizer_type": "ADAM",
    "learning_rate": 0.0007369541599273156,
    "weight_decay": 1e-05,
    "batch_size": 16,
    "dropout": 0.06975319695661708,
    "elapsed_seconds": 22.452282386017032,
    "error": null,
    "x": [
      1.0,
      0.12338607180183588,
      0.4762155324724013,
      0.0,
      1.0,
      1.0,
      0.3903192199646722,
      1.0,
      0.02830360912140776,
      0.2790127878264683
    ]
  },
  {
    "method": "BoTorch",
    "trial": 79,
    "status": "completed",
    "validation_loss": 0.517152726650238,
    "num_layers": 5,
    "hidden_dim": 128,
    "layer_type": "GATED",
    "activation": "RELU",
    "pooling": "MEAN",
    "optimizer_type": "ADAM",
    "learning_rate": 0.0007509845813457065,
    "weight_decay": 1e-05,
    "batch_size": 16,
    "dropout": 0.04451666752253237,
    "elapsed_seconds": 30.779666008951608,
    "error": null,
    "x": [
      1.0,
      0.8810685897719394,
      0.3424689932724934,
      0.24643144236192635,
      1.0,
      0.0,
      0.39850976576623887,
      0.992859812425167,
      0.2563179619635796,
      0.17806667009012947
    ]
  },
  {
    "method": "BoTorch",
    "trial": 80,
    "status": "completed",
    "validation_loss": 0.6548284292221069,
    "num_layers": 5,
    "hidden_dim": 64,
    "layer_type": "GATED",
    "activation": "TANH",
    "pooling": "MEAN",
    "optimizer_type": "ADAM",
    "learning_rate": 0.0024056371344848473,
    "weight_decay": 1e-05,
    "batch_size": 16,
    "dropout": 0.1322540664448831,
    "elapsed_seconds": 20.174487116979435,
    "error": null,
    "x": [
      1.0,
      0.0,
      0.0845317736310937,
      0.8295685900010034,
      1.0,
      0.0,
      0.9041088643873407,
      0.0,
      0.41363164120849794,
      0.5290162657795324
    ]
  },
  {
    "method": "BoTorch",
    "trial": 81,
    "status": "completed",
    "validation_loss": 0.6173261404037476,
    "num_layers": 5,
    "hidden_dim": 64,
    "layer_type": "GATED",
    "activation": "RELU",
    "pooling": "MEAN",
    "optimizer_type": "ADAM",
    "learning_rate": 0.0008006937271672381,
    "weight_decay": 1e-05,
    "batch_size": 32,
    "dropout": 0.09287963049013284,
    "elapsed_seconds": 14.527113422984257,
    "error": null,
    "x": [
      1.0,
      0.1318908259770112,
      0.3875235633044146,
      0.0,
      1.0,
      0.0,
      0.42634517143041306,
      0.18088337556429843,
      0.7080376613921102,
      0.37151852196053137
    ]
  },
  {
    "method": "BoTorch",
    "trial": 82,
    "status": "completed",
    "validation_loss": 0.5582927465438843,
    "num_layers": 5,
    "hidden_dim": 64,
    "layer_type": "GATED",
    "activation": "RELU",
    "pooling": "MEAN",
    "optimizer_type": "ADAM",
    "learning_rate": 0.0009045869426421411,
    "weight_decay": 1e-05,
    "batch_size": 16,
    "dropout": 0.11363335651727867,
    "elapsed_seconds": 35.61098218802363,
    "error": null,
    "x": [
      1.0,
      0.0,
      0.025052069755392516,
      0.0,
      0.7951786630098108,
      1.0,
      0.47932905986490704,
      0.0,
      0.0,
      0.4545334260691147
    ]
  },
  {
    "method": "BoTorch",
    "trial": 83,
    "status": "completed",
    "validation_loss": 0.4978236258029938,
    "num_layers": 5,
    "hidden_dim": 64,
    "layer_type": "GATED",
    "activation": "TANH",
    "pooling": "MEAN",
    "optimizer_type": "ADAM",
    "learning_rate": 0.0014695337884096731,
    "weight_decay": 1e-05,
    "batch_size": 16,
    "dropout": 0.08211484370277636,
    "elapsed_seconds": 29.017142025986686,
    "error": null,
    "x": [
      1.0,
      0.0966623487780829,
      0.3339343697075969,
      1.0,
      1.0,
      0.0,
      0.6900583213651673,
      0.8376689198438598,
      0.2882701081680297,
      0.32845937481110543
    ]
  },
  {
    "method": "BoTorch",
    "trial": 84,
    "status": "completed",
    "validation_loss": 0.6052151322364807,
    "num_layers": 5,
    "hidden_dim": 64,
    "layer_type": "GATED",
    "activation": "TANH",
    "pooling": "MEAN",
    "optimizer_type": "ADAM",
    "learning_rate": 0.00105258391998523,
    "weight_decay": 1e-05,
    "batch_size": 16,
    "dropout": 0.2033040492022325,
    "elapsed_seconds": 29.047089694009628,
    "error": null,
    "x": [
      1.0,
      0.0,
      0.31005420066003997,
      0.9510672151511479,
      1.0,
      0.0,
      0.545135476423286,
      0.0,
      0.27605426551359435,
      0.81321619680893
    ]
  },
  {
    "method": "BoTorch",
    "trial": 85,
    "status": "completed",
    "validation_loss": 0.7929046154022217,
    "num_layers": 5,
    "hidden_dim": 64,
    "layer_type": "GATED",
    "activation": "RELU",
    "pooling": "MEAN",
    "optimizer_type": "ADAM",
    "learning_rate": 0.0027301544012648025,
    "weight_decay": 1e-05,
    "batch_size": 16,
    "dropout": 0.09330802063982226,
    "elapsed_seconds": 20.233442846045364,
    "error": null,
    "x": [
      1.0,
      0.0,
      0.0,
      0.10624080695280105,
      1.0,
      0.0,
      0.9590659541237064,
      0.0,
      0.3949178953440574,
      0.373232082559289
    ]
  },
  {
    "method": "BoTorch",
    "trial": 86,
    "status": "completed",
    "validation_loss": 0.4859398901462555,
    "num_layers": 5,
    "hidden_dim": 64,
    "layer_type": "GATED",
    "activation": "RELU",
    "pooling": "MEAN",
    "optimizer_type": "ADAM",
    "learning_rate": 0.0005886116728676911,
    "weight_decay": 1e-05,
    "batch_size": 16,
    "dropout": 0.054847235143314944,
    "elapsed_seconds": 37.8862740379991,
    "error": null,
    "x": [
      1.0,
      0.29490981508925196,
      0.0,
      0.0,
      1.0,
      0.0,
      0.2927076157040708,
      0.0,
      0.0,
      0.21938894057325978
    ]
  },
  {
    "method": "BoTorch",
    "trial": 87,
    "status": "completed",
    "validation_loss": 0.5791065692901611,
    "num_layers": 5,
    "hidden_dim": 64,
    "layer_type": "GATED",
    "activation": "RELU",
    "pooling": "MEAN",
    "optimizer_type": "ADAM",
    "learning_rate": 0.0012985345993472405,
    "weight_decay": 1e-05,
    "batch_size": 16,
    "dropout": 0.07261032459808595,
    "elapsed_seconds": 15.769023736007512,
    "error": null,
    "x": [
      1.0,
      0.37761676880970446,
      0.0,
      0.0,
      1.0,
      1.0,
      0.6363322711404565,
      0.6880544551773535,
      0.0,
      0.2904412983923438
    ]
  },
  {
    "method": "BoTorch",
    "trial": 88,
    "status": "completed",
    "validation_loss": 0.5657709240913391,
    "num_layers": 5,
    "hidden_dim": 128,
    "layer_type": "GATED",
    "activation": "TANH",
    "pooling": "MEAN",
    "optimizer_type": "ADAM",
    "learning_rate": 0.0003625985432352636,
    "weight_decay": 1e-05,
    "batch_size": 16,
    "dropout": 0.0,
    "elapsed_seconds": 31.298611778998747,
    "error": null,
    "x": [
      1.0,
      0.9537855864049098,
      0.3273492746959599,
      0.5841095880952528,
      1.0,
      1.0,
      0.08230480023520133,
      0.5768774471581651,
      0.04379608234543001,
      0.0
    ]
  },
  {
    "method": "BoTorch",
    "trial": 89,
    "status": "completed",
    "validation_loss": 0.7939319014549255,
    "num_layers": 3,
    "hidden_dim": 128,
    "layer_type": "GAT",
    "activation": "RELU",
    "pooling": "ADD",
    "optimizer_type": "ADAM",
    "learning_rate": 0.00030000000000000014,
    "weight_decay": 1e-05,
    "batch_size": 32,
    "dropout": 0.1570278913748688,
    "elapsed_seconds": 14.753093958017416,
    "error": null,
    "x": [
      0.14082648548160223,
      0.7454566988344462,
      0.9716695908140661,
      0.08756923406779016,
      0.07565668056344693,
      0.0,
      0.0,
      1.0,
      0.5894352930256317,
      0.6281115654994752
    ]
  },
  {
    "method": "BoTorch",
    "trial": 90,
    "status": "completed",
    "validation_loss": 0.6322924494743347,
    "num_layers": 3,
    "hidden_dim": 64,
    "layer_type": "GATED",
    "activation": "TANH",
    "pooling": "MEAN",
    "optimizer_type": "ADAM",
    "learning_rate": 0.0008467295418138465,
    "weight_decay": 1e-05,
    "batch_size": 16,
    "dropout": 0.03250475979678746,
    "elapsed_seconds": 21.96153118502116,
    "error": null,
    "x": [
      0.0,
      0.49586109313776117,
      0.3257953133090046,
      0.7055166817817207,
      1.0,
      0.0,
      0.4506234575533786,
      0.0,
      0.22378162706996904,
      0.13001903918714983
    ]
  },
  {
    "method": "BoTorch",
    "trial": 91,
    "status": "completed",
    "validation_loss": 0.8428304195404053,
    "num_layers": 5,
    "hidden_dim": 64,
    "layer_type": "GAT",
    "activation": "RELU",
    "pooling": "MEAN",
    "optimizer_type": "ADAM",
    "learning_rate": 0.00030000000000000014,
    "weight_decay": 1e-05,
    "batch_size": 16,
    "dropout": 0.0,
    "elapsed_seconds": 51.475010545982514,
    "error": null,
    "x": [
      1.0,
      0.17142234296119668,
      0.5814079779584462,
      0.0,
      1.0,
      1.0,
      0.0,
      0.0,
      0.0,
      0.0
    ]
  },
  {
    "method": "BoTorch",
    "trial": 92,
    "status": "completed",
    "validation_loss": 0.7413520216941833,
    "num_layers": 3,
    "hidden_dim": 64,
    "layer_type": "GATED",
    "activation": "TANH",
    "pooling": "MEAN",
    "optimizer_type": "ADAM",
    "learning_rate": 0.0018834998815549758,
    "weight_decay": 1e-05,
    "batch_size": 16,
    "dropout": 0.10063546483147075,
    "elapsed_seconds": 11.086662529967725,
    "error": null,
    "x": [
      0.28683498058483214,
      0.4459989072974352,
      0.29689461199301753,
      1.0,
      0.6212557408021322,
      0.0,
      0.7978443425087548,
      1.0,
      0.4183477059667198,
      0.402541859325883
    ]
  },
  {
    "method": "BoTorch",
    "trial": 93,
    "status": "completed",
    "validation_loss": 0.8433143496513367,
    "num_layers": 5,
    "hidden_dim": 128,
    "layer_type": "GATED",
    "activation": "TANH",
    "pooling": "ADD",
    "optimizer_type": "ADAM",
    "learning_rate": 0.0022253135264832247,
    "weight_decay": 1e-05,
    "batch_size": 32,
    "dropout": 0.25,
    "elapsed_seconds": 13.247150521026924,
    "error": null,
    "x": [
      1.0,
      1.0,
      0.4155102245933581,
      1.0,
      0.0,
      0.0,
      0.8702699530598009,
      0.0,
      1.0,
      1.0
    ]
  },
  {
    "method": "BoTorch",
    "trial": 94,
    "status": "completed",
    "validation_loss": 0.7587363123893738,
    "num_layers": 5,
    "hidden_dim": 64,
    "layer_type": "GATED",
    "activation": "RELU",
    "pooling": "MEAN",
    "optimizer_type": "ADAM",
    "learning_rate": 0.0008871010983336247,
    "weight_decay": 1e-05,
    "batch_size": 16,
    "dropout": 0.1292416282509993,
    "elapsed_seconds": 22.32301626104163,
    "error": null,
    "x": [
      1.0,
      0.0,
      0.1325837810946744,
      0.3575798109480679,
      1.0,
      0.0,
      0.47085186223318215,
      0.0,
      0.0,
      0.5169665130039972
    ]
  },
  {
    "method": "BoTorch",
    "trial": 95,
    "status": "completed",
    "validation_loss": 0.8673108220100403,
    "num_layers": 4,
    "hidden_dim": 64,
    "layer_type": "GATED",
    "activation": "TANH",
    "pooling": "ADD",
    "optimizer_type": "ADAM",
    "learning_rate": 0.0012060443192700144,
    "weight_decay": 1e-05,
    "batch_size": 16,
    "dropout": 0.24076164055717175,
    "elapsed_seconds": 14.9080554539687,
    "error": null,
    "x": [
      0.484870486627154,
      0.10615675212293817,
      0.14852471561038177,
      1.0,
      0.0,
      0.4405740097527268,
      0.6042420126705005,
      0.8291829832545752,
      0.3510738964908145,
      0.963046562228687
    ]
  },
  {
    "method": "BoTorch",
    "trial": 96,
    "status": "completed",
    "validation_loss": 0.7066761255264282,
    "num_layers": 5,
    "hidden_dim": 128,
    "layer_type": "GATED",
    "activation": "RELU",
    "pooling": "MEAN",
    "optimizer_type": "ADAM",
    "learning_rate": 0.00030000000000000014,
    "weight_decay": 1e-05,
    "batch_size": 16,
    "dropout": 0.05539466803181155,
    "elapsed_seconds": 32.96603887603851,
    "error": null,
    "x": [
      1.0,
      0.7891123801868295,
      0.2801340111788895,
      0.0,
      1.0,
      1.0,
      0.0,
      1.0,
      0.0027699678532703393,
      0.2215786721272462
    ]
  },
  {
    "method": "BoTorch",
    "trial": 97,
    "status": "completed",
    "validation_loss": 0.8835528492927551,
    "num_layers": 5,
    "hidden_dim": 64,
    "layer_type": "GATED",
    "activation": "TANH",
    "pooling": "MEAN",
    "optimizer_type": "ADAM",
    "learning_rate": 0.0007252520625234488,
    "weight_decay": 1e-05,
    "batch_size": 16,
    "dropout": 0.07474562109660274,
    "elapsed_seconds": 18.133720938989427,
    "error": null,
    "x": [
      1.0,
      0.0,
      0.3729989124615084,
      1.0,
      1.0,
      1.0,
      0.38336771783436213,
      0.0,
      0.45696456544799324,
      0.29898248438641095
    ]
  },
  {
    "method": "BoTorch",
    "trial": 98,
    "status": "completed",
    "validation_loss": 0.6515367031097412,
    "num_layers": 5,
    "hidden_dim": 64,
    "layer_type": "GATED",
    "activation": "RELU",
    "pooling": "MEAN",
    "optimizer_type": "ADAM",
    "learning_rate": 0.0016980407176664617,
    "weight_decay": 1e-05,
    "batch_size": 16,
    "dropout": 0.07521649762817893,
    "elapsed_seconds": 20.126148023002315,
    "error": null,
    "x": [
      1.0,
      0.17691286579875884,
      0.35601945705498517,
      0.0,
      1.0,
      0.0,
      0.7528268453495437,
      1.0,
      0.3894874417156311,
      0.30086599051271573
    ]
  },
  {
    "method": "BoTorch",
    "trial": 99,
    "status": "completed",
    "validation_loss": 0.5151379704475403,
    "num_layers": 5,
    "hidden_dim": 64,
    "layer_type": "GATED",
    "activation": "TANH",
    "pooling": "MEAN",
    "optimizer_type": "ADAM",
    "learning_rate": 0.0015532054996074977,
    "weight_decay": 1e-05,
    "batch_size": 16,
    "dropout": 0.18219351799615938,
    "elapsed_seconds": 35.54573249700479,
    "error": null,
    "x": [
      1.0,
      0.0,
      0.40968258836596105,
      1.0,
      1.0,
      0.0,
      0.714107664911855,
      1.0,
      0.0,
      0.7287740719846375
    ]
  },
  {
    "method": "BoTorch",
    "trial": 100,
    "status": "completed",
    "validation_loss": 0.67388516664505,
    "num_layers": 5,
    "hidden_dim": 64,
    "layer_type": "GATED",
    "activation": "TANH",
    "pooling": "MEAN",
    "optimizer_type": "ADAM",
    "learning_rate": 0.0020364948269536672,
    "weight_decay": 1e-05,
    "batch_size": 16,
    "dropout": 0.25,
    "elapsed_seconds": 31.203674589982256,
    "error": null,
    "x": [
      1.0,
      0.20251151079187407,
      0.40139672288562334,
      1.0,
      1.0,
      1.0,
      0.8317620565212438,
      0.0,
      0.1644330370436609,
      1.0
    ]
  },
  {
    "method": "BoTorch",
    "trial": 101,
    "status": "completed",
    "validation_loss": 0.6113771200180054,
    "num_layers": 5,
    "hidden_dim": 128,
    "layer_type": "GATED",
    "activation": "RELU",
    "pooling": "MEAN",
    "optimizer_type": "ADAM",
    "learning_rate": 0.00030000000000000014,
    "weight_decay": 1e-05,
    "batch_size": 16,
    "dropout": 0.04304352155128735,
    "elapsed_seconds": 30.770543332968373,
    "error": null,
    "x": [
      1.0,
      0.9145081753623993,
      0.4006927752865241,
      0.0,
      1.0,
      1.0,
      0.0,
      0.0,
      0.3884147035008278,
      0.1721740862051494
    ]
  },
  {
    "method": "BoTorch",
    "trial": 102,
    "status": "completed",
    "validation_loss": 0.7851712703704834,
    "num_layers": 3,
    "hidden_dim": 64,
    "layer_type": "GATED",
    "activation": "RELU",
    "pooling": "ADD",
    "optimizer_type": "ADAM",
    "learning_rate": 0.0006286893226174394,
    "weight_decay": 1e-05,
    "batch_size": 16,
    "dropout": 0.027973557658351324,
    "elapsed_seconds": 22.719974819978233,
    "error": null,
    "x": [
      0.0,
      0.31394424336017807,
      0.0,
      0.0,
      0.0,
      0.0,
      0.3213148298269546,
      0.0,
      0.14731694643238427,
      0.1118942306334053
    ]
  },
  {
    "method": "BoTorch",
    "trial": 103,
    "status": "completed",
    "validation_loss": 0.816487193107605,
    "num_layers": 5,
    "hidden_dim": 128,
    "layer_type": "GATED",
    "activation": "RELU",
    "pooling": "MEAN",
    "optimizer_type": "ADAM",
    "learning_rate": 0.00030000000000000014,
    "weight_decay": 1e-05,
    "batch_size": 16,
    "dropout": 0.13248775300657767,
    "elapsed_seconds": 26.43187902099453,
    "error": null,
    "x": [
      1.0,
      0.5252708519509695,
      0.4465920403068476,
      0.0,
      1.0,
      1.0,
      0.0,
      0.0,
      0.0,
      0.5299510120263107
    ]
  },
  {
    "method": "BoTorch",
    "trial": 104,
    "status": "completed",
    "validation_loss": 0.5385368466377258,
    "num_layers": 5,
    "hidden_dim": 128,
    "layer_type": "GATED",
    "activation": "RELU",
    "pooling": "MEAN",
    "optimizer_type": "ADAM",
    "learning_rate": 0.0003078678072868132,
    "weight_decay": 1e-05,
    "batch_size": 16,
    "dropout": 0.0,
    "elapsed_seconds": 38.065819990006275,
    "error": null,
    "x": [
      1.0,
      1.0,
      0.0,
      0.0,
      1.0,
      1.0,
      0.011243023827418258,
      0.0,
      0.0,
      0.0
    ]
  },
  {
    "method": "BoTorch",
    "trial": 105,
    "status": "completed",
    "validation_loss": 0.6317670345306396,
    "num_layers": 5,
    "hidden_dim": 64,
    "layer_type": "GATED",
    "activation": "TANH",
    "pooling": "MEAN",
    "optimizer_type": "ADAM",
    "learning_rate": 0.00078029887985313,
    "weight_decay": 1e-05,
    "batch_size": 16,
    "dropout": 0.2351128227627847,
    "elapsed_seconds": 26.744090018968564,
    "error": null,
    "x": [
      1.0,
      0.0,
      0.0,
      0.6212221877304004,
      1.0,
      0.0,
      0.4151397287511029,
      0.0,
      0.0,
      0.9404512910511388
    ]
  },
  {
    "method": "BoTorch",
    "trial": 106,
    "status": "completed",
    "validation_loss": 0.6019280552864075,
    "num_layers": 5,
    "hidden_dim": 64,
    "layer_type": "GATED",
    "activation": "TANH",
    "pooling": "MEAN",
    "optimizer_type": "ADAM",
    "learning_rate": 0.0015913186560123484,
    "weight_decay": 1e-05,
    "batch_size": 16,
    "dropout": 0.0779019247325388,
    "elapsed_seconds": 21.48099228303181,
    "error": null,
    "x": [
      1.0,
      0.0,
      0.1233404213137977,
      1.0,
      1.0,
      1.0,
      0.7246358995911245,
      1.0,
      0.0,
      0.3116076989301552
    ]
  },
  {
    "method": "BoTorch",
    "trial": 107,
    "status": "completed",
    "validation_loss": 0.8421970009803772,
    "num_layers": 5,
    "hidden_dim": 64,
    "layer_type": "GATED",
    "activation": "TANH",
    "pooling": "MEAN",
    "optimizer_type": "ADAM",
    "learning_rate": 0.003000000000000001,
    "weight_decay": 1e-05,
    "batch_size": 16,
    "dropout": 0.021053838384784213,
    "elapsed_seconds": 25.963525206025224,
    "error": null,
    "x": [
      1.0,
      0.4491462389144003,
      0.36173249833417787,
      1.0,
      1.0,
      0.0,
      1.0,
      1.0,
      0.0,
      0.08421535353913685
    ]
  },
  {
    "method": "BoTorch",
    "trial": 108,
    "status": "completed",
    "validation_loss": 0.7430970072746277,
    "num_layers": 5,
    "hidden_dim": 64,
    "layer_type": "GATED",
    "activation": "TANH",
    "pooling": "ADD",
    "optimizer_type": "ADAM",
    "learning_rate": 0.0021849049608287916,
    "weight_decay": 1e-05,
    "batch_size": 16,
    "dropout": 0.19649751506493987,
    "elapsed_seconds": 32.68179295497248,
    "error": null,
    "x": [
      1.0,
      0.0,
      0.4248691683479325,
      1.0,
      0.0,
      0.0,
      0.8623112960214239,
      0.0,
      0.0,
      0.7859900602597595
    ]
  },
  {
    "method": "BoTorch",
    "trial": 109,
    "status": "completed",
    "validation_loss": 0.6007837653160095,
    "num_layers": 3,
    "hidden_dim": 128,
    "layer_type": "GATED",
    "activation": "RELU",
    "pooling": "MEAN",
    "optimizer_type": "ADAM",
    "learning_rate": 0.00030000000000000014,
    "weight_decay": 1e-05,
    "batch_size": 16,
    "dropout": 0.0,
    "elapsed_seconds": 25.194186717038974,
    "error": null,
    "x": [
      0.0,
      0.656361922781398,
      0.34910730200154955,
      0.0,
      1.0,
      0.0,
      0.0,
      1.0,
      0.28193344477982935,
      0.0
    ]
  },
  {
    "method": "BoTorch",
    "trial": 110,
    "status": "completed",
    "validation_loss": 0.5074545741081238,
    "num_layers": 3,
    "hidden_dim": 64,
    "layer_type": "GATED",
    "activation": "RELU",
    "pooling": "MEAN",
    "optimizer_type": "ADAM",
    "learning_rate": 0.0013617161257957323,
    "weight_decay": 1e-05,
    "batch_size": 32,
    "dropout": 0.25,
    "elapsed_seconds": 17.994656896975357,
    "error": null,
    "x": [
      0.0,
      0.10337798572794979,
      0.3690549897167044,
      0.0,
      0.7882191975130574,
      0.0,
      0.6569653258012577,
      1.0,
      0.6262279119347849,
      1.0
    ]
  },
  {
    "method": "BoTorch",
    "trial": 111,
    "status": "completed",
    "validation_loss": 0.6032936573028564,
    "num_layers": 3,
    "hidden_dim": 64,
    "layer_type": "GATED",
    "activation": "TANH",
    "pooling": "MEAN",
    "optimizer_type": "ADAM",
    "learning_rate": 0.0007687414929882095,
    "weight_decay": 1e-05,
    "batch_size": 16,
    "dropout": 0.25,
    "elapsed_seconds": 20.36560240300605,
    "error": null,
    "x": [
      0.0,
      0.41406686893346806,
      0.3572108651938864,
      1.0,
      0.8657956079446978,
      0.0,
      0.40865906812075964,
      1.0,
      0.0,
      1.0
    ]
  },
  {
    "method": "BoTorch",
    "trial": 112,
    "status": "completed",
    "validation_loss": 0.5941222310066223,
    "num_layers": 3,
    "hidden_dim": 64,
    "layer_type": "GATED",
    "activation": "TANH",
    "pooling": "MEAN",
    "optimizer_type": "ADAM",
    "learning_rate": 0.0011660056760106172,
    "weight_decay": 1e-05,
    "batch_size": 32,
    "dropout": 0.20772193270979386,
    "elapsed_seconds": 14.125384729006328,
    "error": null,
    "x": [
      0.0,
      0.24291018813917575,
      0.3728255439137307,
      1.0,
      1.0,
      0.0,
      0.5895794098149028,
      1.0,
      1.0,
      0.8308877308391754
    ]
  },
  {
    "method": "BoTorch",
    "trial": 113,
    "status": "completed",
    "validation_loss": 0.6500736474990845,
    "num_layers": 5,
    "hidden_dim": 128,
    "layer_type": "GATED",
    "activation": "RELU",
    "pooling": "MEAN",
    "optimizer_type": "ADAM",
    "learning_rate": 0.0005183499510210376,
    "weight_decay": 1e-05,
    "batch_size": 32,
    "dropout": 0.0,
    "elapsed_seconds": 18.214675934053957,
    "error": null,
    "x": [
      1.0,
      0.7425303022859778,
      0.0,
      0.0,
      1.0,
      0.0,
      0.2375018071152745,
      1.0,
      1.0,
      0.0
    ]
  },
  {
    "method": "BoTorch",
    "trial": 114,
    "status": "completed",
    "validation_loss": 0.5708010196685791,
    "num_layers": 3,
    "hidden_dim": 64,
    "layer_type": "GATED",
    "activation": "RELU",
    "pooling": "MEAN",
    "optimizer_type": "ADAM",
    "learning_rate": 0.0007154636158591893,
    "weight_decay": 1e-05,
    "batch_size": 16,
    "dropout": 0.0244345236242879,
    "elapsed_seconds": 26.570128350984305,
    "error": null,
    "x": [
      0.0,
      0.0,
      0.19798108085877797,
      0.0,
      0.8232007134074519,
      0.0,
      0.37746629835396833,
      1.0,
      0.0,
      0.0977380944971516
    ]
  },
  {
    "method": "BoTorch",
    "trial": 115,
    "status": "completed",
    "validation_loss": 0.6453995108604431,
    "num_layers": 5,
    "hidden_dim": 64,
    "layer_type": "GAT",
    "activation": "RELU",
    "pooling": "MEAN",
    "optimizer_type": "ADAM",
    "learning_rate": 0.00030000000000000014,
    "weight_decay": 1e-05,
    "batch_size": 16,
    "dropout": 0.15743798427107064,
    "elapsed_seconds": 93.034740171046,
    "error": null,
    "x": [
      1.0,
      0.0,
      0.9888870704331675,
      0.0,
      1.0,
      0.0,
      0.0,
      1.0,
      0.0,
      0.6297519370842826
    ]
  },
  {
    "method": "BoTorch",
    "trial": 116,
    "status": "completed",
    "validation_loss": 0.7631444931030273,
    "num_layers": 5,
    "hidden_dim": 64,
    "layer_type": "GAT",
    "activation": "RELU",
    "pooling": "ADD",
    "optimizer_type": "ADAM",
    "learning_rate": 0.00030000000000000014,
    "weight_decay": 1e-05,
    "batch_size": 16,
    "dropout": 0.05310158313378682,
    "elapsed_seconds": 81.38790828996571,
    "error": null,
    "x": [
      1.0,
      0.4222485509820087,
      0.5015331939775103,
      0.0,
      0.0,
      1.0,
      0.0,
      0.0,
      0.0,
      0.2124063325351473
    ]
  },
  {
    "method": "BoTorch",
    "trial": 117,
    "status": "completed",
    "validation_loss": 0.5566040277481079,
    "num_layers": 5,
    "hidden_dim": 128,
    "layer_type": "GATED",
    "activation": "RELU",
    "pooling": "MEAN",
    "optimizer_type": "ADAM",
    "learning_rate": 0.0005992396931064675,
    "weight_decay": 1e-05,
    "batch_size": 16,
    "dropout": 0.050621375341560824,
    "elapsed_seconds": 41.655400999996345,
    "error": null,
    "x": [
      1.0,
      0.6596762952437139,
      0.0,
      0.0,
      1.0,
      1.0,
      0.30047931820633456,
      0.0,
      0.0,
      0.2024855013662433
    ]
  },
  {
    "method": "BoTorch",
    "trial": 118,
    "status": "completed",
    "validation_loss": 0.9701180458068848,
    "num_layers": 5,
    "hidden_dim": 64,
    "layer_type": "GAT",
    "activation": "RELU",
    "pooling": "ADD",
    "optimizer_type": "ADAM",
    "learning_rate": 0.0008482109470203903,
    "weight_decay": 1e-05,
    "batch_size": 16,
    "dropout": 0.15451817292773146,
    "elapsed_seconds": 16.436580593988765,
    "error": null,
    "x": [
      1.0,
      0.0,
      0.96942606578623,
      0.0,
      0.0,
      0.0,
      0.4513826184498543,
      1.0,
      0.0,
      0.6180726917109258
    ]
  },
  {
    "method": "BoTorch",
    "trial": 119,
    "status": "completed",
    "validation_loss": 1.01566481590271,
    "num_layers": 3,
    "hidden_dim": 64,
    "layer_type": "GATED",
    "activation": "RELU",
    "pooling": "ADD",
    "optimizer_type": "ADAM",
    "learning_rate": 0.0008220235071525943,
    "weight_decay": 1e-05,
    "batch_size": 16,
    "dropout": 0.25,
    "elapsed_seconds": 11.110695233976003,
    "error": null,
    "x": [
      0.0,
      0.0,
      0.36399763160199594,
      0.0,
      0.22777022563708837,
      1.0,
      0.4377629823832629,
      1.0,
      0.0,
      1.0
    ]
  },
  {
    "method": "BoTorch",
    "trial": 120,
    "status": "completed",
    "validation_loss": 0.7893855571746826,
    "num_layers": 5,
    "hidden_dim": 128,
    "layer_type": "GATED",
    "activation": "RELU",
    "pooling": "MEAN",
    "optimizer_type": "ADAM",
    "learning_rate": 0.0005861031201410342,
    "weight_decay": 1e-05,
    "batch_size": 16,
    "dropout": 0.033457429768521896,
    "elapsed_seconds": 19.880738185020164,
    "error": null,
    "x": [
      1.0,
      0.5983705626810548,
      0.3377732210545402,
      0.0,
      0.6915757501483624,
      0.0,
      0.2908527786504001,
      1.0,
      0.0,
      0.13382971907408758
    ]
  },
  {
    "method": "BoTorch",
    "trial": 121,
    "status": "completed",
    "validation_loss": 0.5438369512557983,
    "num_layers": 5,
    "hidden_dim": 128,
    "layer_type": "GATED",
    "activation": "RELU",
    "pooling": "MEAN",
    "optimizer_type": "ADAM",
    "learning_rate": 0.0005257486363318468,
    "weight_decay": 1e-05,
    "batch_size": 16,
    "dropout": 0.0,
    "elapsed_seconds": 31.454793576034717,
    "error": null,
    "x": [
      1.0,
      0.6756993429664765,
      0.0,
      0.0,
      1.0,
      0.3359018094168127,
      0.24365690018254355,
      1.0,
      0.0,
      0.0
    ]
  },
  {
    "method": "BoTorch",
    "trial": 122,
    "status": "completed",
    "validation_loss": 0.7608874440193176,
    "num_layers": 3,
    "hidden_dim": 64,
    "layer_type": "GATED",
    "activation": "TANH",
    "pooling": "MEAN",
    "optimizer_type": "ADAM",
    "learning_rate": 0.001310673708607779,
    "weight_decay": 1e-05,
    "batch_size": 32,
    "dropout": 0.20408415785117898,
    "elapsed_seconds": 10.27730503398925,
    "error": null,
    "x": [
      0.0,
      0.47522666123792345,
      0.38111617911752865,
      0.5644617844677899,
      1.0,
      0.0,
      0.6403733330889962,
      1.0,
      0.5337057424654871,
      0.8163366314047159
    ]
  },
  {
    "method": "BoTorch",
    "trial": 123,
    "status": "completed",
    "validation_loss": 0.6724022030830383,
    "num_layers": 3,
    "hidden_dim": 64,
    "layer_type": "GATED",
    "activation": "RELU",
    "pooling": "MEAN",
    "optimizer_type": "ADAM",
    "learning_rate": 0.003000000000000001,
    "weight_decay": 1e-05,
    "batch_size": 32,
    "dropout": 0.25,
    "elapsed_seconds": 7.1623181300237775,
    "error": null,
    "x": [
      0.0,
      0.0,
      0.4147355803402032,
      0.0,
      1.0,
      0.0,
      1.0,
      1.0,
      1.0,
      1.0
    ]
  },
  {
    "method": "BoTorch",
    "trial": 124,
    "status": "completed",
    "validation_loss": 1.5198127031326294,
    "num_layers": 3,
    "hidden_dim": 64,
    "layer_type": "GAT",
    "activation": "TANH",
    "pooling": "MEAN",
    "optimizer_type": "ADAM",
    "learning_rate": 0.00030000000000000014,
    "weight_decay": 1e-05,
    "batch_size": 32,
    "dropout": 0.12082633241800228,
    "elapsed_seconds": 22.967292414978147,
    "error": null,
    "x": [
      0.0,
      0.03709477714756581,
      0.9760395211318913,
      1.0,
      1.0,
      0.0,
      0.0,
      1.0,
      1.0,
      0.4833053296720091
    ]
  },
  {
    "method": "BoTorch",
    "trial": 125,
    "status": "completed",
    "validation_loss": 0.492442786693573,
    "num_layers": 5,
    "hidden_dim": 64,
    "layer_type": "GATED",
    "activation": "TANH",
    "pooling": "MEAN",
    "optimizer_type": "ADAM",
    "learning_rate": 0.0014009036387377766,
    "weight_decay": 1e-05,
    "batch_size": 32,
    "dropout": 0.25,
    "elapsed_seconds": 20.083045480016153,
    "error": null,
    "x": [
      1.0,
      0.0,
      0.33173680904346775,
      0.5729658690762841,
      1.0,
      0.0,
      0.6692870086148496,
      1.0,
      1.0,
      1.0
    ]
  },
  {
    "method": "BoTorch",
    "trial": 126,
    "status": "completed",
    "validation_loss": 0.6818921566009521,
    "num_layers": 5,
    "hidden_dim": 128,
    "layer_type": "GAT",
    "activation": "RELU",
    "pooling": "MEAN",
    "optimizer_type": "ADAM",
    "learning_rate": 0.00030000000000000014,
    "weight_decay": 1e-05,
    "batch_size": 16,
    "dropout": 0.15847112977770336,
    "elapsed_seconds": 68.5040932620177,
    "error": null,
    "x": [
      1.0,
      1.0,
      0.9253734685497631,
      0.0,
      1.0,
      0.0,
      0.0,
      1.0,
      0.0,
      0.6338845191108134
    ]
  },
  {
    "method": "BoTorch",
    "trial": 127,
    "status": "completed",
    "validation_loss": 0.9605687260627747,
    "num_layers": 3,
    "hidden_dim": 64,
    "layer_type": "GATED",
    "activation": "RELU",
    "pooling": "MEAN",
    "optimizer_type": "ADAM",
    "learning_rate": 0.00030000000000000014,
    "weight_decay": 1e-05,
    "batch_size": 16,
    "dropout": 0.0,
    "elapsed_seconds": 15.126805294014048,
    "error": null,
    "x": [
      0.0,
      0.0,
      0.2040390851757222,
      0.3022461219961303,
      1.0,
      0.0,
      0.0,
      0.0,
      0.0,
      0.0
    ]
  },
  {
    "method": "BoTorch",
    "trial": 128,
    "status": "completed",
    "validation_loss": 0.8051719069480896,
    "num_layers": 5,
    "hidden_dim": 64,
    "layer_type": "GATED",
    "activation": "TANH",
    "pooling": "ADD",
    "optimizer_type": "ADAM",
    "learning_rate": 0.0016139972304035123,
    "weight_decay": 1e-05,
    "batch_size": 32,
    "dropout": 0.25,
    "elapsed_seconds": 10.947085035033524,
    "error": null,
    "x": [
      1.0,
      0.0,
      0.3625324697847958,
      1.0,
      0.13933741321584173,
      0.0,
      0.7307815304238218,
      1.0,
      0.7952547457622412,
      1.0
    ]
  },
  {
    "method": "BoTorch",
    "trial": 129,
    "status": "completed",
    "validation_loss": 0.5594171285629272,
    "num_layers": 5,
    "hidden_dim": 64,
    "layer_type": "GATED",
    "activation": "RELU",
    "pooling": "MEAN",
    "optimizer_type": "ADAM",
    "learning_rate": 0.0011083451071570898,
    "weight_decay": 1e-05,
    "batch_size": 32,
    "dropout": 0.25,
    "elapsed_seconds": 13.420138325018343,
    "error": null,
    "x": [
      1.0,
      0.27073823316036,
      0.324008744424399,
      0.0,
      1.0,
      0.0,
      0.5675537536850881,
      0.0,
      1.0,
      1.0
    ]
  },
  {
    "method": "BoTorch",
    "trial": 130,
    "status": "completed",
    "validation_loss": 0.6963568329811096,
    "num_layers": 5,
    "hidden_dim": 128,
    "layer_type": "GATED",
    "activation": "RELU",
    "pooling": "MEAN",
    "optimizer_type": "ADAM",
    "learning_rate": 0.0004999328295032178,
    "weight_decay": 1e-05,
    "batch_size": 16,
    "dropout": 0.0,
    "elapsed_seconds": 18.98332743003266,
    "error": null,
    "x": [
      1.0,
      0.6904145585773875,
      0.0,
      0.0,
      1.0,
      0.0,
      0.22179040214484158,
      0.0,
      0.3606878049611197,
      0.0
    ]
  },
  {
    "method": "BoTorch",
    "trial": 131,
    "status": "completed",
    "validation_loss": 0.6106017231941223,
    "num_layers": 3,
    "hidden_dim": 64,
    "layer_type": "GATED",
    "activation": "RELU",
    "pooling": "MEAN",
    "optimizer_type": "ADAM",
    "learning_rate": 0.0026218752632259272,
    "weight_decay": 1e-05,
    "batch_size": 32,
    "dropout": 0.25,
    "elapsed_seconds": 13.374606219003908,
    "error": null,
    "x": [
      0.0,
      0.0,
      0.2547731729178061,
      0.0,
      1.0,
      0.0,
      0.9414907713905855,
      0.0,
      1.0,
      1.0
    ]
  },
  {
    "method": "BoTorch",
    "trial": 132,
    "status": "completed",
    "validation_loss": 0.5778921842575073,
    "num_layers": 5,
    "hidden_dim": 64,
    "layer_type": "GATED",
    "activation": "RELU",
    "pooling": "MEAN",
    "optimizer_type": "ADAM",
    "learning_rate": 0.0010154705912548744,
    "weight_decay": 1e-05,
    "batch_size": 16,
    "dropout": 0.08477719925994255,
    "elapsed_seconds": 22.39877238398185,
    "error": null,
    "x": [
      1.0,
      0.0,
      0.0,
      0.32985595310057875,
      1.0,
      0.0,
      0.5295460957285288,
      1.0,
      0.0,
      0.3391087970397702
    ]
  },
  {
    "method": "BoTorch",
    "trial": 133,
    "status": "completed",
    "validation_loss": 0.6217531561851501,
    "num_layers": 5,
    "hidden_dim": 128,
    "layer_type": "GAT",
    "activation": "RELU",
    "pooling": "ADD",
    "optimizer_type": "ADAM",
    "learning_rate": 0.00030000000000000014,
    "weight_decay": 1e-05,
    "batch_size": 16,
    "dropout": 0.05879167290364297,
    "elapsed_seconds": 87.7707888459554,
    "error": null,
    "x": [
      1.0,
      1.0,
      0.7633606107969056,
      0.0,
      0.3730002854054745,
      1.0,
      0.0,
      1.0,
      0.0,
      0.23516669161457188
    ]
  },
  {
    "method": "BoTorch",
    "trial": 134,
    "status": "completed",
    "validation_loss": 0.5461184978485107,
    "num_layers": 5,
    "hidden_dim": 64,
    "layer_type": "GATED",
    "activation": "RELU",
    "pooling": "MEAN",
    "optimizer_type": "ADAM",
    "learning_rate": 0.0014022805935926114,
    "weight_decay": 1e-05,
    "batch_size": 32,
    "dropout": 0.25,
    "elapsed_seconds": 13.460497135994956,
    "error": null,
    "x": [
      1.0,
      0.0,
      0.07397701504508862,
      0.050484028346219775,
      1.0,
      0.0,
      0.6697136690793919,
      0.0,
      1.0,
      1.0
    ]
  },
  {
    "method": "BoTorch",
    "trial": 135,
    "status": "completed",
    "validation_loss": 0.6114380955696106,
    "num_layers": 5,
    "hidden_dim": 64,
    "layer_type": "GATED",
    "activation": "RELU",
    "pooling": "MEAN",
    "optimizer_type": "ADAM",
    "learning_rate": 0.001671760080041845,
    "weight_decay": 1e-05,
    "batch_size": 16,
    "dropout": 0.25,
    "elapsed_seconds": 20.222881818015594,
    "error": null,
    "x": [
      1.0,
      0.0,
      0.12283677939844082,
      0.0,
      1.0,
      0.0,
      0.7460526957814676,
      1.0,
      0.0,
      1.0
    ]
  },
  {
    "method": "BoTorch",
    "trial": 136,
    "status": "completed",
    "validation_loss": 0.530757486820221,
    "num_layers": 5,
    "hidden_dim": 64,
    "layer_type": "GATED",
    "activation": "TANH",
    "pooling": "MEAN",
    "optimizer_type": "ADAM",
    "learning_rate": 0.001478797861022385,
    "weight_decay": 1e-05,
    "batch_size": 32,
    "dropout": 0.23060477840086108,
    "elapsed_seconds": 17.89867427397985,
    "error": null,
    "x": [
      1.0,
      0.0,
      0.06264511423229112,
      0.831216311158251,
      1.0,
      0.0,
      0.6927875590052862,
      0.0,
      1.0,
      0.9224191136034443
    ]
  },
  {
    "method": "BoTorch",
    "trial": 137,
    "status": "completed",
    "validation_loss": 0.6994076371192932,
    "num_layers": 3,
    "hidden_dim": 128,
    "layer_type": "GATED",
    "activation": "TANH",
    "pooling": "MEAN",
    "optimizer_type": "ADAM",
    "learning_rate": 0.00030000000000000014,
    "weight_decay": 1e-05,
    "batch_size": 16,
    "dropout": 0.03636795456846473,
    "elapsed_seconds": 26.29394282400608,
    "error": null,
    "x": [
      0.0,
      0.7493116479433672,
      0.37906029205608466,
      0.670426631853934,
      1.0,
      1.0,
      0.0,
      1.0,
      0.0,
      0.1454718182738589
    ]
  },
  {
    "method": "BoTorch",
    "trial": 138,
    "status": "completed",
    "validation_loss": 0.5952893495559692,
    "num_layers": 3,
    "hidden_dim": 64,
    "layer_type": "GATED",
    "activation": "RELU",
    "pooling": "MEAN",
    "optimizer_type": "ADAM",
    "learning_rate": 0.0005605836031281411,
    "weight_decay": 1e-05,
    "batch_size": 16,
    "dropout": 0.04567303164784904,
    "elapsed_seconds": 28.18555271200603,
    "error": null,
    "x": [
      0.0,
      0.18826505770592353,
      0.0,
      0.0,
      1.0,
      1.0,
      0.27151913593059085,
      1.0,
      0.0,
      0.18269212659139616
    ]
  },
  {
    "method": "BoTorch",
    "trial": 139,
    "status": "completed",
    "validation_loss": 0.4868628978729248,
    "num_layers": 5,
    "hidden_dim": 64,
    "layer_type": "GATED",
    "activation": "RELU",
    "pooling": "MEAN",
    "optimizer_type": "ADAM",
    "learning_rate": 0.0011761696454664935,
    "weight_decay": 1e-05,
    "batch_size": 32,
    "dropout": 0.20153868180185305,
    "elapsed_seconds": 21.21271034696838,
    "error": null,
    "x": [
      1.0,
      0.0,
      0.0496156141142046,
      0.39053832549176265,
      1.0,
      1.0,
      0.5933487122384562,
      1.0,
      1.0,
      0.8061547272074122
    ]
  },
  {
    "method": "BoTorch",
    "trial": 140,
    "status": "completed",
    "validation_loss": 1.198630928993225,
    "num_layers": 5,
    "hidden_dim": 64,
    "layer_type": "GATED",
    "activation": "RELU",
    "pooling": "MEAN",
    "optimizer_type": "ADAM",
    "learning_rate": 0.0009562557298493477,
    "weight_decay": 1e-05,
    "batch_size": 32,
    "dropout": 0.20517267156469576,
    "elapsed_seconds": 6.8234359950292856,
    "error": null,
    "x": [
      1.0,
      0.0,
      0.0,
      0.0,
      1.0,
      0.0,
      0.5034527957264542,
      1.0,
      1.0,
      0.820690686258783
    ]
  },
  {
    "method": "BoTorch",
    "trial": 141,
    "status": "completed",
    "validation_loss": 0.5254628658294678,
    "num_layers": 5,
    "hidden_dim": 64,
    "layer_type": "GATED",
    "activation": "RELU",
    "pooling": "MEAN",
    "optimizer_type": "ADAM",
    "learning_rate": 0.0019138892583419743,
    "weight_decay": 1e-05,
    "batch_size": 32,
    "dropout": 0.25,
    "elapsed_seconds": 15.679262783029117,
    "error": null,
    "x": [
      1.0,
      0.0,
      0.11774989480265355,
      0.3927173318623387,
      1.0,
      1.0,
      0.8047955502559611,
      0.0,
      1.0,
      1.0
    ]
  },
  {
    "method": "BoTorch",
    "trial": 142,
    "status": "completed",
    "validation_loss": 0.5736843347549438,
    "num_layers": 3,
    "hidden_dim": 64,
    "layer_type": "GATED",
    "activation": "TANH",
    "pooling": "MEAN",
    "optimizer_type": "ADAM",
    "learning_rate": 0.0013138969716856724,
    "weight_decay": 1e-05,
    "batch_size": 16,
    "dropout": 0.2031066788072527,
    "elapsed_seconds": 21.91600904101506,
    "error": null,
    "x": [
      0.0,
      0.0,
      0.0631966530481649,
      0.7104198361889444,
      1.0,
      1.0,
      0.6414400569404343,
      0.0,
      0.0,
      0.8124267152290108
    ]
  },
  {
    "method": "BoTorch",
    "trial": 143,
    "status": "completed",
    "validation_loss": 0.4879865348339081,
    "num_layers": 5,
    "hidden_dim": 64,
    "layer_type": "GATED",
    "activation": "RELU",
    "pooling": "MEAN",
    "optimizer_type": "ADAM",
    "learning_rate": 0.000934303204728525,
    "weight_decay": 1e-05,
    "batch_size": 16,
    "dropout": 0.048034056818251125,
    "elapsed_seconds": 33.45442560798256,
    "error": null,
    "x": [
      1.0,
      0.0,
      0.0,
      0.3826619622720863,
      1.0,
      1.0,
      0.49336658379247167,
      0.0,
      0.0,
      0.1921362272730045
    ]
  },
  {
    "method": "BoTorch",
    "trial": 144,
    "status": "completed",
    "validation_loss": 0.5612751841545105,
    "num_layers": 3,
    "hidden_dim": 64,
    "layer_type": "GATED",
    "activation": "TANH",
    "pooling": "MEAN",
    "optimizer_type": "ADAM",
    "learning_rate": 0.0017489682780216394,
    "weight_decay": 1e-05,
    "batch_size": 16,
    "dropout": 0.09186680252720936,
    "elapsed_seconds": 17.30491120397346,
    "error": null,
    "x": [
      0.0,
      0.0,
      0.3741071281266054,
      0.5794657658062757,
      1.0,
      0.0,
      0.7656606777978396,
      1.0,
      0.0,
      0.3674672101088374
    ]
  },
  {
    "method": "BoTorch",
    "trial": 145,
    "status": "completed",
    "validation_loss": 0.6002861857414246,
    "num_layers": 5,
    "hidden_dim": 64,
    "layer_type": "GATED",
    "activation": "RELU",
    "pooling": "MEAN",
    "optimizer_type": "ADAM",
    "learning_rate": 0.0013237262507661885,
    "weight_decay": 1e-05,
    "batch_size": 32,
    "dropout": 0.25,
    "elapsed_seconds": 13.464559104002547,
    "error": null,
    "x": [
      1.0,
      0.0,
      0.18138225218732046,
      0.2650038554206708,
      1.0,
      1.0,
      0.6446769267027965,
      1.0,
      1.0,
      1.0
    ]
  },
  {
    "method": "BoTorch",
    "trial": 146,
    "status": "completed",
    "validation_loss": 0.9571533799171448,
    "num_layers": 5,
    "hidden_dim": 64,
    "layer_type": "GATED",
    "activation": "RELU",
    "pooling": "MEAN",
    "optimizer_type": "ADAM",
    "learning_rate": 0.003000000000000001,
    "weight_decay": 1e-05,
    "batch_size": 32,
    "dropout": 0.25,
    "elapsed_seconds": 6.838225184008479,
    "error": null,
    "x": [
      1.0,
      0.0,
      0.10775582136150923,
      0.24247614350632632,
      1.0,
      0.0,
      1.0,
      0.0,
      1.0,
      1.0
    ]
  },
  {
    "method": "BoTorch",
    "trial": 147,
    "status": "completed",
    "validation_loss": 0.6900511384010315,
    "num_layers": 5,
    "hidden_dim": 64,
    "layer_type": "GAT",
    "activation": "RELU",
    "pooling": "ADD",
    "optimizer_type": "ADAM",
    "learning_rate": 0.00030000000000000014,
    "weight_decay": 1e-05,
    "batch_size": 16,
    "dropout": 0.04930045493654662,
    "elapsed_seconds": 81.03377944097156,
    "error": null,
    "x": [
      1.0,
      0.0,
      0.7810106980980072,
      0.0,
      0.0,
      1.0,
      0.0,
      0.0,
      0.0,
      0.19720181974618647
    ]
  },
  {
    "method": "BoTorch",
    "trial": 148,
    "status": "completed",
    "validation_loss": 0.6263554096221924,
    "num_layers": 5,
    "hidden_dim": 64,
    "layer_type": "GATED",
    "activation": "TANH",
    "pooling": "MEAN",
    "optimizer_type": "ADAM",
    "learning_rate": 0.0009800540096683186,
    "weight_decay": 1e-05,
    "batch_size": 32,
    "dropout": 0.20842640239077678,
    "elapsed_seconds": 17.884207191993482,
    "error": null,
    "x": [
      1.0,
      0.0,
      0.04176221818260419,
      1.0,
      1.0,
      1.0,
      0.5141287551101676,
      0.0,
      1.0,
      0.8337056095631071
    ]
  },
  {
    "method": "BoTorch",
    "trial": 149,
    "status": "completed",
    "validation_loss": 0.677811324596405,
    "num_layers": 3,
    "hidden_dim": 64,
    "layer_type": "GATED",
    "activation": "RELU",
    "pooling": "MEAN",
    "optimizer_type": "ADAM",
    "learning_rate": 0.0012180072758861426,
    "weight_decay": 1e-05,
    "batch_size": 16,
    "dropout": 0.096077628207087,
    "elapsed_seconds": 20.397668429010082,
    "error": null,
    "x": [
      0.0,
      0.0,
      0.06282948320269655,
      0.47122603143927055,
      1.0,
      1.0,
      0.6085286278857037,
      0.0,
      0.0,
      0.384310512828348
    ]
  }
]